Workbook
Name xldm: [3]字典代码表!$C$2:$D$7

Sheet MxSim.MultiPhy多物理场耦合产品基线
A1: L3 | B1: L4功能大类 | C1: L5功能子类 | D1: L6功能名称 （包含已有功能） | E1: 关键规格与描述 （如有可能，尽量定量指标描述） | F1: 对标软件 （具体到模块名，可为多个软件） | G1: 对标国外软件成熟度评价% （7级为基本满足日常使用需求，9级为成熟完全满足工程应用需求） 需要指出功能指标、功能差距 | H1: 规划年度 | I1: 基线达到时间（月） | J1: 隶属版本号 | K1: 预期人力成本（人月） （如：P1 2人月， P2 1人月） | L1: 行业/工业品需求分类 （通用类、XX行业/XX产品专用） | M1: 重难点评述
A2: MxSim.MultiPhy多物理场耦合分析平台 | B2: 外部模型 | C2: 几何 | D2: 基本建模功能集成 | E2: 具备基本的几何建模功能 | F2: Ansys Workbench | G2: 7级 | H2: 2024年度 | I2: 2024.12 | J2: MxSim.MultiPhy V2.0.0 | K2: P1 2人月 P2 2人月 | L2: 通用
D3: 常用几何模型导入 | E3: 支持常见的几何文件导入 | F3: Ansys Workbench | G3: 7级 | H3: 2023年度 | I3: 2023.12 | J3: MxSim.MultiPhy V1.0.0 | K3: P1 1人月 | L3: 通用
C4: 网格 | D4: 常用网格模型导入 | E4: 支持常见CAE文件网格模型的导入 | F4: Ansys Workbench | G4: 7级 | H4: 2023年度 | I4: 2023.12 | J4: MxSim.MultiPhy V1.0.0 | K4: P1 1人月 | L4: 通用
D5: 网格剖分集成 | E5: 具备基本的网格剖分功能 | F5: Ansys Workbench | G5: 7级 | H5: 2024年度 | I5: 2024.12 | J5: MxSim.MultiPhy V2.0.0 | K5: P1 1人月 P2 2人月 | L5: 通用
B6: MxSim单物理场仿真 | C6: 低频电磁场 | D6: 静电场 | E6: 用于处理静态电场问题，例如电场分析、电势分析等。可以计算电荷分布、电势分布、电场强度分布等 | F6: Ansys Workbench Maxwell | G6: 8级 功能具备，效率待提升 | H6: 2023年度 | I6: 2023.6 | J6: MxSim.MultiPhy V1.0.0 | K6: P1 2人月 P3 3人月 | L6: 通用
D7: 直流电场 | E7: 用于处理直流电场问题，例如电流、电势和电场分布等。可以计算电阻、电容、电感等元件的特性 | F7: Ansys Workbench Maxwell | G7: 8级 功能具备，效率待提升 | H7: 2023年度 | I7: 2023.6 | J7: MxSim.MultiPhy V1.0.0 | L7: 通用
D8: 交流电池 | E8: 用于处理交流电场问题，例如电源、电感、电容和负载等元件的特性。可以计算电流、电势和电场分布等 | F8: Ansys Workbench Maxwell | G8: 8级 功能具备，效率待提升 | H8: 2023年度 | I8: 2023.6 | J8: MxSim.MultiPhy V1.0.0 | L8: 通用
D9: 静磁场 | E9: 用于处理静态磁场问题，例如磁场分析、磁通密度分析等。可以计算磁荷分布、磁势分布、磁场强度分布等 | F9: Ansys Workbench Maxwell | G9: 8级 功能具备，效率待提升 | H9: 2023年度 | I9: 2023.6 | J9: MxSim.MultiPhy V1.0.0 | L9: 通用
D10: 似稳电磁场 | E10: 用于处理低频电磁场问题，例如电磁波导、共振腔等器件的特性。可以计算电流、电势和电场分布等 | F10: Ansys Workbench Maxwell | G10: 8级 功能具备，效率待提升 | H10: 2023年度 | I10: 2023.6 | J10: MxSim.MultiPhy V1.0.0 | L10: 通用
D11: 瞬态磁场 | E11: 用于处理高速电磁场问题，例如磁控管、脉冲电磁铁等器件的特性。可以计算感应电压、电流和磁场分布等 | F11: Ansys Workbench Maxwell | G11: 8级 功能具备，效率待提升 | H11: 2023年度 | I11: 2023.6 | J11: MxSim.MultiPhy V1.0.0 | L11: 通用
C12: 高频电磁场 | D12: 频域分析 | E12: 使用频域分析，可以计算各种高频器件的S参数、传输线参数、阻抗等，并可进行频率扫描、功率扫描等操作 | F12: Ansys Workbench HFSS | G12: 7级 | H12: 2025年度 | I12: 2025.12 | J12: MxSim.MultiPhy V3.0.0 | K12: P1 2人月 P3 2人月 | L12: 通用
D13: 时域分析 | E13: 使用时域分析，可以计算电磁波的传播、反射、折射等问题，还可以检测和分析器件中的故障或损伤 | F13: Ansys Workbench HFSS | G13: 7级 | H13: 2025年度 | I13: 2025.12 | J13: MxSim.MultiPhy V3.0.0 | L13: 通用
C14: 通用结构 | D14: 静态结构 | E14: 用于处理静态结构问题，例如强度、刚度、变形等方面的问题。可以计算应力、位移、变形等 | F14: Ansys Workbench Mechanical | G14: 8级 核心功能具备，但复杂功能存在差距 | H14: 2023年度 | I14: 2023.9 | J14: MxSim.MultiPhy V1.0.0 | K14: P1 2人月 P3 3人月 | L14: 通用
D15: 瞬态结构 | E15: 用于处理结构在短时间内发生变化的问题，例如冲击、爆炸等。可以计算结构响应的瞬态特性 | F15: Ansys Workbench Mechanical | G15: 8级 核心功能具备，但复杂功能存在差距 | H15: 2023年度 | I15: 2023.9 | J15: MxSim.MultiPhy V1.0.0 | L15: 通用
D16: 模态 | E16: 用于计算结构的固有频率和振型，并可视化振型形状。可以帮助用户理解结构的动态特性 | F16: Ansys Workbench Mechanical | G16: 8级 核心功能具备，但复杂功能存在差距 | H16: 2023年度 | I16: 2023.9 | J16: MxSim.MultiPhy V1.0.0 | L16: 通用
D17: 响应谱 | E17: 用于评估结构在地震等外部激励下的响应情况。可以计算结构的最大应力、最大位移等参数 | F17: Ansys Workbench Mechanical | G17: 8级 核心功能具备，但复杂功能存在差距 | H17: 2023年度 | I17: 2023.9 | J17: MxSim.MultiPhy V1.0.0 | L17: 通用
D18: 谐波响应 | E18: 用于分析结构在周期性载荷作用下的响应情况。可以计算结构的共振频率、响应幅值等参数 | F18: Ansys Workbench Mechanical | G18: 8级 核心功能具备，但复杂功能存在差距 | H18: 2023年度 | I18: 2023.9 | J18: MxSim.MultiPhy V1.0.0 | L18: 通用
D19: 随机振动 | E19: 用于分析结构在随机载荷下的响应情况。可以计算结构的振幅谱、功率谱密度等参数 | F19: Ansys Workbench Mechanical | G19: 8级 核心功能具备，但复杂功能存在差距 | H19: 2023年度 | I19: 2023.9 | J19: MxSim.MultiPhy V1.0.0 | L19: 通用
C20: 热 | D20: 稳态热 | E20: 用于处理稳态热传导和温度分布问题。可以计算稳定状态下物体的温度、热流、热通量等参数 | F20: Ansys Workbench Mechanical | G20: 8级 核心功能具备，但复杂功能存在差距 | H20: 2023年度 | I20: 2023.1 | J20: MxSim.MultiPhy V1.0.0 | K20: P1 1人月 P3 1人月 | L20: 通用
D21: 瞬态热 | E21: 用于处理热响应时间较短的问题，例如瞬态加热、冷却等。可以计算在特定时间下物体的温度、热流、热通量等参数 | F21: Ansys Workbench Mechanical | G21: 8级 核心功能具备，但复杂功能存在差距 | H21: 2023年度 | I21: 2023.1 | J21: MxSim.MultiPhy V1.0.0 | L21: 通用
C22: 显式动力学 | D22: 显式动力学 | E22: 用于分析高速碰撞、爆炸和冲击等领域中的结构动态响应。该模块采用显式时间积分方法，可用于模拟非线性、大变形和破坏行为。 | F22: Ansys Workbench Dyna | G22: 8级 核心功能具备，但复杂功能存在差距 | H22: 2024年度 | I22: 2024.9 | J22: MxSim.MultiPhy V2.0.0 | K22: P1 1人月 P3 2人月 | L22: 通用
C23: 流体 | D23: 不可压 | E23: 用于处理速度较低、密度变化小的流体问题，例如液体流动、液压系统等。可以计算流量、压力、速度场等参数 | F23: Ansys Workbench Fluent | G23: 8级 核心功能具备，但复杂功能存在差距 | H23: 2024年度 | I23: 2024.12 | J23: MxSim.MultiPhy V2.0.0 | K23: P1 2人月 P3 2人月 | L23: 通用
D24: 可压 | E24: 用于处理速度较高、密度变化大的流体问题，例如空气动力学、喷气推进等。可以计算压力波、激波、速度场等参数 | F24: Ansys Workbench Fluent | G24: 8级 核心功能具备，但复杂功能存在差距 | H24: 2024年度 | I24: 2024.12 | J24: MxSim.MultiPhy V2.0.0 | L24: 通用
D25: 气动声 | E25: 用于处理空气产生的声音问题，例如飞机噪声、风扇噪声等。可以计算声功率、声压级等参数 | F25: Ansys Workbench Fluent | G25: 8级 核心功能具备，但复杂功能存在差距 | H25: 2025年度 | I25: 依托单场求解器进度，计划2025.12 | J25: MxSim.MultiPhy V3.0.0 | K25: P1 1人月 P3 1人月 | L25: 通用
C26: 刚体动力学 | D26: 刚体动力学 | E26: 用于分析机械系统或结构件的运动和响应。该模块采用牛顿力学原理，可用于模拟多种刚体运动问题，例如碰撞、滚动、旋转等 | F26: Ansys Workbench | G26: 7级 依托单场求解器功能 | H26: 2025年度 | I26: 依托单场求解器进度，计划2025.12 | J26: MxSim.MultiPhy V3.0.0 | K26: P1 1人月 P3 3人月 | L26: 通用
C27: 声学 | D27: 静态声学 | E27: 静态声学分析通常使用单一频率进行求解，可以选择感兴趣的频率范围进行分析。 | F27: Ansys Workbench Mechanical | G27: 8级 核心功能具备，但复杂功能存在差距 | H27: 2024年度 | I27: 2024.9 | J27: MxSim.MultiPhy V2.0.0 | K27: P1 2人月 P3 2人月 | L27: 通用
D28: 模态声学 | E28: 用于确定声腔的固有频率和振型 | F28: Ansys Workbench Mechanical | G28: 8级 核心功能具备，但复杂功能存在差距 | H28: 2024年度 | I28: 2024.9 | J28: MxSim.MultiPhy V2.0.0 | L28: 通用
D29: 谐波声学 | E29: 用于评估声波在结构中的传播，以及在不同频率下结构的响应 | F29: Ansys Workbench Mechanical | G29: 8级 核心功能具备，但复杂功能存在差距 | H29: 2024年度 | I29: 2024.9 | J29: MxSim.MultiPhy V2.0.0 | L29: 通用
D30: 瞬态声学 | E30: 用于评估声波传播时结构的响应，例如冲击或爆炸声 | F30: Ansys Workbench Mechanical | G30: 8级 核心功能具备，但复杂功能存在差距 | H30: 2024年度 | I30: 2024.9 | J30: MxSim.MultiPhy V2.0.0 | L30: 通用
C31: 疲劳 | D31: 疲劳模块 | E31: 分析动态荷载下的应力、应变分布，并进行疲劳寿命预测 | F31: Ansys Workbench ncode | G31: 8级 核心功能具备，但复杂功能存在差距 | H31: 2025年度 | I31: 依托单场求解器进度，计划2025.12 | J31: MxSim.MultiPhy V3.0.0 | K31: P1 2人月 P3 2人月 | L31: 通用
B32: 多物理场耦合仿真 | C32: 顺序耦合 | D32: 结构-热 | E32: 用于处理由热载荷引起的结构变形问题。可以计算热源对结构的影响，同时还考虑结构对温度场的反馈作用 | F32: Ansys Workbench | G32: 7级 | H32: 2023年度 | I32: 2023.12 | J32: MxSim.MultiPhy V1.0.0 | K32: P1 1人月 P3 2人月 | L32: 通用
D33: 结构-磁 | E33: 将结构和磁场分析相互耦合，以考虑磁场对结构材料的影响 | F33: Ansys Workbench | G33: 7级 | H33: 2023年度 | I33: 2023.1 | J33: MxSim.MultiPhy V1.0.0 | L33: 通用
D34: 热-电 | E34: 电流通过导体时会产生热量，同时热量也会影响材料的电阻率和电导率等电特性 | F34: Ansys Workbench | G34: 7级 | H34: 2023年度 | I34: 2023.12 | J34: MxSim.MultiPhy V1.0.0 | L34: 通用
D35: 电磁-热 | E35: 用于处理电磁场和热传导的耦合问题，例如电炉、感应加热器等 | F35: Ansys Workbench | G35: 7级 | H35: 2023年度 | I35: 2023.12 | J35: MxSim.MultiPhy V1.0.0 | L35: 通用
D36: 结构-流体 | E36: 用于处理结构和流体的耦合问题，例如风力发电机、船舶等。 | F36: Ansys Workbench | G36: 7级 | H36: 2024年度 | I36: 2024.12 | J36: MxSim.MultiPhy V2.0.0 | K36: P1 1人月 P3 3人月 | L36: 通用
D37: 结构-声 | E37: 用于处理结构和声波的耦合问题，例如机器噪声、声学隔离等。 | F37: Ansys Workbench | G37: 7级 | H37: 2024年度 | I37: 2024.12 | J37: MxSim.MultiPhy V2.0.0 | L37: 通用
D38: 热-流 | E38: 热和流体分析相互耦合，以考虑流体对温度场的影响 | F38: Ansys Workbench | G38: 7级 | H38: 2024年度 | I38: 2024.12 | J38: MxSim.MultiPhy V2.0.0 | L38: 通用
D39: 电磁-流体 | E39: 用于处理电磁场和流体流动的耦合问题，例如电磁泵、电磁阀等 | F39: Ansys Workbench | G39: 7级 | H39: 2024年度 | I39: 2024.12 | J39: MxSim.MultiPhy V2.0.0 | L39: 通用
D40: 电磁-声 | E40: 用于处理电磁场和声波的耦合问题，例如扬声器、电动汽车等 | F40: Ansys Workbench | G40: 7级 | H40: 2024年度 | I40: 2024.12 | J40: MxSim.MultiPhy V2.0.0 | L40: 通用
D41: 显式动力学-流体 | E41: 用于处理显式动力学和流体流动的耦合问题，例如爆炸物冲击波等 | F41: Ansys Workbench | G41: 7级 | H41: 2024年度 | I41: 2024.12 | J41: MxSim.MultiPhy V2.0.0 | K41: P1 1人月 P3 3人月 | L41: 通用
D42: 显式动力学-热 | E42: 用于处理显式动力学和热传导的耦合问题，例如高速撞击等 | F42: Ansys Workbench | G42: 7级 | H42: 2024年度 | I42: 2024.12 | J42: MxSim.MultiPhy V2.0.0 | L42: 通用
D43: 显式动力学-结构 | E43: 用于处理显式动力学和结构响应的耦合问题，例如高强度碰撞等 | F43: Ansys Workbench | G43: 7级 | H43: 2024年度 | I43: 2024.12 | J43: MxSim.MultiPhy V2.0.0 | L43: 通用
D44: 显式动力学-磁 | E44: 用于处理显式动力学和磁场的耦合问题，例如爆炸产生的电磁干扰等 | F44: Ansys Workbench | G44: 7级 | H44: 2024年度 | I44: 2024.12 | J44: MxSim.MultiPhy V2.0.0 | L44: 通用
C45: 直接耦合 | D45: 结构-热 | E45: 用于处理结构和热传导的直接耦合问题，例如建筑物、汽车引擎等 | F45: Ansys Workbench | G45: 7级 | H45: 2023年度 | I45: 2023.12 | J45: MxSim.MultiPhy V1.0.0 | K45: P3 1人月 | L45: 通用
D46: 结构-电 | E46: 用于处理结构和电场的直接耦合问题，例如电气设备、电子器件等 | F46: Ansys Workbench | G46: 7级 | H46: 2024年度 | I46: 2024.12 | J46: MxSim.MultiPhy V2.0.0 | K46: P1 1人月 P3 2人月 | L46: 通用
D47: 结构-声 | E47: 用于处理结构和声波的直接耦合问题 | F47: Ansys Workbench | G47: 7级 | H47: 2024年度 | I47: 2024.12 | J47: MxSim.MultiPhy V2.0.0 | L47: 通用
D48: 热-流 | E48: 用于处理热传导和流体流动之间的直接耦合问题，例如换热器、涡轮机等 | F48: Ansys Workbench | G48: 7级 | H48: 2025年度 | I48: 2025.12 | J48: MxSim.MultiPhy V3.0.0 | L48: 通用
D49: 结构-磁 | E49: 用于处理结构和磁场的直接耦合问题，例如变压器、电机等 | F49: Ansys Workbench | G49: 7级 | H49: 2025年度 | I49: 2025.12 | J49: MxSim.MultiPhy V3.0.0 | K49: P3 3人月 | L49: 通用
D50: 热-电 | E50: 用于处理热传导和电场之间的直接耦合问题，例如电子散热器、温控系统等 | F50: Ansys Workbench | G50: 7级 | H50: 2025年度 | I50: 2025.12 | J50: MxSim.MultiPhy V3.0.0 | L50: 通用
D51: 任意强耦合形式 | E51: 分块矩阵的形式，实现任意场的强耦合框架，该阶段以架构为主，需要依赖耦合矩阵的构建 | F51: Comsol | G51: 7级 | H51: 2025年度 | I51: 2025.12 | J51: MxSim.MultiPhy V3.0.0 | K51: P3 3人月 | L51: 通用
B52: 基本结果后处理 | C52: 结果显示 | D52: 云图 | E52: 通过颜色编码显示场量的强度分布，例如温度、应力等 | F52: Ansys Workbench | G52: 9级 | H52: 2023年度 | I52: 2023.12 | J52: MxSim.MultiPhy V1.0.0 | K52: P1 2人月 | L52: 通用
D53: 动画 | E53: 将仿真过程转换为视频或GIF动画，帮助用户观察系统行为的变化 | F53: Ansys Workbench | G53: 9级 | H53: 2023年度 | I53: 2023.12 | J53: MxSim.MultiPhy V1.0.0 | L53: 通用
D54: 图表 | E54: 绘制各种曲线和数据图表，例如应力-应变曲线、频谱图等 | F54: Ansys Workbench | G54: 9级 | H54: 2023年度 | I54: 2023.12 | J54: MxSim.MultiPhy V1.0.0 | L54: 通用
D55: 切片 | E55: 在体积内绘制平面切片，以查看特定位置上的场量分布 | F55: Ansys Workbench | G55: 9级 | H55: 2023年度 | I55: 2023.12 | J55: MxSim.MultiPhy V1.0.0 | L55: 通用
D56: 矢量图 | E56: 绘制矢量场，例如速度矢量场、电场矢量场等 | F56: Ansys Workbench | G56: 9级 | H56: 2023年度 | I56: 2023.12 | J56: MxSim.MultiPhy V1.0.0 | L56: 通用
H60: 2023年度 | K60: P1 10人月 P3 10人月 | L60: 包含界面工作P1 10人月
H61: 2024年度 | K61: P1 11人月 P2 4人月 P3 14人月 | L61: 包含界面人员 P1 11人月
H62: 2025年度 | K62: P1 6人月 P3 14人月 | L62: 包含界面人员 P1 6人月

Sheet MxSim.Acoustic-声学仿真产品基线
A1: L3 | B1: L4功能大类 | C1: L5功能子类 | D1: L6功能名称 | E1: 关键规格与描述 （如有可能，尽量定量指标描述） | F1: 对标国外软件 （具体到模块名） | G1: 对标国外软件成熟度评价% （7级为基本满足日常使用需求，9级为成熟完全满足工程应用需求） 需要指出功能指标、功能差距 | H1: 规划年度 | I1: 基线达到时间（月） | J1: 隶属版本号 | K1: 预期人力成本（人月） （如：P1 2人月， P2 1人月） | L1: 行业/工业品需求分类 （通用类、XX行业/XX产品专用） | M1: 重难点评述
B2: 网格功能需求 | C2: 声学网格功能 | D2: AML边界层网格 | E2: 基于模型边界自动生成吸声边界层网格，不显示，但在计算过程中使用 | F2: LMS Virtual Lab_Acoustic | G2: 7级 | H2: 2025年度 | I2: 2025.12 | J2: MxSim.Acoustic V2.0.0 | K2: P2 2人月 | L2: 通用 | M2: 需网格技术支持
D3: 网格包络 | E3: 声学网格包络面，声学有限元分析中是所有体网格的表面包围面，用于添加各种求解设置；声学边界元方法中的网格包络面就是等于声学边界元分析网格 | F3: LMS Virtual Lab_Acoustic | G3: 7级 | H3: 2025年度 | I3: 2025.12 | J3: MxSim.Acoustic V2.0.0 | K3: P2 1人月 | L3: 通用
B4: 声学材料 | C4: 声学材料 | D4: 基本声学介质 | E4: 传播速度、介质的质量密度参数 | F4: LMS Virtual Lab_Acoustic | G4: 9级 | H4: 2023年度 | I4: 2023.12 | J4: MxSim.Acoustic V1.0.0 | K4: P1 1人月 | L4: 通用
D5: 均质材料 | E5: 设置密度、声速、阻尼等参数来定义 | F5: LMS Virtual Lab_Acoustic | G5: 9级 | H5: 2023年度 | I5: 2023.12 | J5: MxSim.Acoustic V1.0.0 | L5: 通用
D6: 异质材料 | E6: 定义每个组成部分的材料和几何形状，以及各部分之间的界面条件 | F6: LMS Virtual Lab_Acoustic | G6: 7级 | H6: 2024年度 | I6: 2024.12 | J6: MxSim.Acoustic V1.0.0 | K6: P2 3人月 | L6: 通用
D7: 吸声材料 | E7: 设置材料的吸收系数和厚度等参数 | F7: LMS Virtual Lab_Acoustic | G7: 7级 | H7: 2024年度 | I7: 2024.12 | J7: MxSim.Acoustic V1.0.0 | L7: 通用
D8: 隔声材料 | E8: 设置材料的传声系数和厚度等参数 | F8: LMS Virtual Lab_Acoustic | G8: 7级 | H8: 2024年度 | I8: 2024.12 | J8: MxSim.Acoustic V1.0.0 | L8: 通用
D9: 散射材料 | E9: 设置材料的散射截面和表面形态等参数 | F9: LMS Virtual Lab_Acoustic | G9: 7级 | H9: 2024年度 | I9: 2024.12 | J9: MxSim.Acoustic V1.0.0 | L9: 通用
D10: 多孔材料 | E10: 定义材料的孔隙率、孔洞形状、孔洞分布等参数 | F10: LMS Virtual Lab_Acoustic | G10: 7级 | H10: 2025年度 | I10: 2025.12 | J10: MxSim.Acoustic V2.0.0 | K10: P2 1人月 | L10: 通用
B11: 声学边界条件 | C11: 常规边界条件 | D11: 声压边界 | E11: 设置声压 | F11: LMS Virtual Lab_Acoustic | G11: 9级 | H11: 2023年度 | I11: 2023.12 | J11: MxSim.Acoustic V1.0.0 | K11: P1 0.5人月 | L11: 通用
D12: 阻抗边界 | E12: 模拟声学场景中不同材质之间反射和吸收声波的特性的功能，设置所需的阻抗值或频率响应函数等参数 | F12: LMS Virtual Lab_Acoustic | G12: 7级 | H12: 2024年度 | I12: 2024.6 | J12: MxSim.Acoustic V1.0.0 | K12: P1 1人月 | L12: 通用
C13: 专用边界条件 | D13: 自由边界条件 | E13: 模拟无限远处的声场，适用于开放空间中的声学问题 | F13: LMS Virtual Lab_Acoustic | G13: 7级 | H13: 2024年度 | I13: 2024.6 | J13: MxSim.Acoustic V1.0.0 | K13: P2 2人月 | L13: 通用
D14: 刚性壁面边界条件 | E14: 模拟完全反射的表面，适用于封闭空间中的声学问题 | F14: LMS Virtual Lab_Acoustic | G14: 7级 | H14: 2024年度 | I14: 2024.6 | J14: MxSim.Acoustic V1.0.0 | K14: P2 1人月 | L14: 通用
D15: 半无限介质边界条件 | E15: 模拟介质边界处的声波传播，适用于介质分界面附近的声学问题 | F15: LMS Virtual Lab_Acoustic | G15: 7级 | H15: 2024年度 | I15: 2024.12 | J15: MxSim.Acoustic V1.0.0 | K15: P2 1人月 | L15: 通用
D16: 吸声壁面边界条 | E16: 模拟具有一定吸声能力的表面，适用于需要考虑墙面吸声效果的声学问题 | F16: LMS Virtual Lab_Acoustic | G16: 7级 | H16: 2024年度 | I16: 2024.12 | J16: MxSim.Acoustic V1.0.0 | K16: P2 1人月 | L16: 通用
D17: 周期性边界条件 | E17: 模拟具有周期性结构的声学系统，适用于声学器件和振动系统中的周期性问题 | F17: LMS Virtual Lab_Acoustic | G17: 7级 | H17: 2025年度 | I17: 2025.12 | J17: MxSim.Acoustic V2.0.0 | K17: P2 1人月 | L17: 通用
D18: 对称边界条 | E18: 模拟对称结构中的声波传播，适用于对称结构中的声学问题 | F18: LMS Virtual Lab_Acoustic | G18: 7级 | H18: 2025年度 | I18: 2025.12 | J18: MxSim.Acoustic V2.0.0 | K18: P2 1人月 | L18: 通用
B19: 声场激励 | C19: 声源 | D19: 单极子 | E19: 通过设置其位置、振幅、相位等参数来进行定义和模拟 | F19: LMS Virtual Lab_Acoustic | G19: 7级 | H19: 2024年度 | I19: 2024.12 | J19: MxSim.Acoustic V1.0.0 | K19: P2 1人月 | L19: 通用
D20: 偶极子 | E20: 通过设置其位置、振幅、相位等参数来进行定义和模拟 | F20: LMS Virtual Lab_Acoustic | G20: 7级 | H20: 2024年度 | I20: 2024.12 | J20: MxSim.Acoustic V1.0.0 | L20: 通用
D21: 平面波 | E21: 通过设置其位置、振幅、相位等参数来进行定义和模拟 | F21: LMS Virtual Lab_Acoustic | G21: 7级 | H21: 2024年度 | I21: 2024.12 | J21: MxSim.Acoustic V1.0.0 | K21: P2 1人月 | L21: 通用
C22: 激励 | D22: 速度 | E22: 通过施加速度变化来模拟声波在介质中的传播，设置所需的波形类型、频率、幅值等参数 | F22: LMS Virtual Lab_Acoustic | G22: 9级 | H22: 2023年度 | I22: 2023.12 | J22: MxSim.Acoustic V1.0.0 | K22: P1 1人月 | L22: 通用
D23: 加速度 | E23: 通过施加加速度变化来模拟声波在介质中的传播，设置所需的波形类型、频率、幅值等参数 | F23: LMS Virtual Lab_Acoustic | G23: 9级 | H23: 2023年度 | I23: 2023.12 | J23: MxSim.Acoustic V1.0.0 | L23: 通用
B24: 分析类型及方法 | C24: 声学边界元 | D24: 时域分析 | E24: 时域分析 | F24: LMS Virtual Lab_Acoustic_BEM | G24: 7级 | H24: 2024年度 | I24: 2024.12 | J24: MxSim.Acoustic V1.0.0 | K24: P2 1人月 | L24: 通用
D25: 频域分析 | E25: 频域分析 | F25: LMS Virtual Lab_Acoustic_BEM | G25: 7级 | H25: 2024年度 | I25: 2024.6 | J25: MxSim.Acoustic V1.0.0 | K25: P2 1人月 | L25: 通用
D26: ACA迭代法 | E26: 支持ACA（自适应交叉近似）迭代法 | F26: LMS Virtual Lab_Acoustic_BEM | G26: 7级 | H26: 2025年度 | I26: 2025.12 | J26: MxSim.Acoustic V2.0.0 | K26: P3 1人月 | L26: 通用
D27: FMM迭代法 | E27: 支持FMM（快速多极子）迭代法 | F27: LMS Virtual Lab_Acoustic_BEM | G27: 7级 | H27: 2025年度 | I27: 2025.12 | J27: MxSim.Acoustic V2.0.0 | K27: P3 1人月 | L27: 通用
D28: HFBEM直接法 | E28: 支持HFBEM (高频BEM)直接法 | F28: LMS Virtual Lab_Acoustic_BEM | G28: 7级 | H28: 2025年度 | I28: 2025.12 | J28: MxSim.Acoustic V2.0.0 | K28: P3 2人月 | L28: 通用
D29: ATM （即TPA） | E29: 支持ATM (Acoustic Transfer Matrix)计算，适用于声学方面的路径计算分析（即TPA） | F29: LMS Virtual Lab_Acoustic_BEM | G29: 7级 | H29: 2025年度 | I29: 2025.12 | J29: MxSim.Acoustic V2.0.0 | K29: P3 1人月 | L29: 通用
C30: 声学有限元 | D30: 频域有分析 | E30: 内声场 | F30: LMS Virtual Lab_Acoustic_FEM | G30: 9级 | H30: 2023年度 | I30: 2023.12 | J30: MxSim.Acoustic V1.0.0 | K30: P1 2人月 | L30: 通用
E31: 外声场，支持完美边界层PML计算 | F31: LMS Virtual Lab_Acoustic_FEM | G31: 7级 | H31: 2023年度 | I31: 2023.12 | J31: MxSim.Acoustic V1.0.0 | K31: P2 1人月 | L31: 通用
E32: 外声场，支持AML计算，即求解器自动生成PML层 | F32: LMS Virtual Lab_Acoustic_FEM | G32: 7级 | H32: 2025年度 | I32: 2025.12 | J32: MxSim.Acoustic V2.0.0 | K32: P2 2人月 | L32: 通用
D33: 时域分析 | E33: 内声场分析 | F33: LMS Virtual Lab_Acoustic_FEM | G33: 7级 | H33: 2024年度 | I33: 2024.6 | J33: MxSim.Acoustic V1.0.0 | K33: P2 1人月 | L33: 通用
D34: 声模态分析 | E34: 声模态分析 | F34: LMS Virtual Lab_Acoustic_FEM | G34: 7级 | H34: 2023年度 | I34: 2023.12 | J34: MxSim.Acoustic V1.0.0 | K34: P1 1人月 | L34: 通用
C35: 能量分析法 | D35: SEA模块 | E35: 高频声场分析 | F35: LMS Virtual Lab_Acoustic_FEM | G35: 7级 | H35: 2025年度 | I35: 2025.12 | J35: MxSim.Acoustic V2.0.0 | K35: P3 6人月 | L35: 通用 | M35: 最基本的高频分析方法，具体技术细节需后续更新
B36: 网格类型 | C36: 网格类型 | D36: 2D | E36: 三角形 | F36: LMS Virtual Lab_Acoustic | G36: 9级 | H36: 2023年度 | I36: 2023.12 | J36: MxSim.Acoustic V1.0.0 | K36: P1 0.5人月 | L36: 通用
E37: 四边形 | F37: LMS Virtual Lab_Acoustic | G37: 7级 | H37: 2024年度 | I37: 2024.6 | J37: MxSim.Acoustic V1.0.0 | K37: P1 1人月 | L37: 通用
D38: 3D | E38: 四面体网格 | F38: LMS Virtual Lab_Acoustic | G38: 9级 | H38: 2023年度 | I38: 2023.12 | J38: MxSim.Acoustic V1.0.0 | K38: P1 0.5人月 | L38: 通用
E39: 三棱柱网格 | F39: LMS Virtual Lab_Acoustic | G39: 7级 | H39: 2024年度 | I39: 2024.6 | J39: MxSim.Acoustic V1.0.0 | K39: P1 1人月 | L39: 通用
E40: 六面体网格 | F40: LMS Virtual Lab_Acoustic | G40: 7级 | H40: 2024年度 | I40: 2024.6 | J40: MxSim.Acoustic V1.0.0 | K40: P1 1人月 | L40: 通用
B41: 声学结果输出 | C41: 声学结果 | D41: 声压等输出 | E41: 支持输出声压，声压级，加权声压级（A-weighted），速度，声功率等 | F41: LMS Virtual Lab_Acoustic | G41: 9级 | H41: 2024年度 | I41: 2024.6 | J41: MxSim.Acoustic V1.0.0 | K41: P2 1人月 | L41: 通用
D42: 远场结果输出 | E42: 支持远场声压（级），声功率，声指向性等输出 | F42: LMS Virtual Lab_Acoustic | G42: 7级 | H42: 2024年度 | I42: 2024.6 | J42: MxSim.Acoustic V1.0.0 | K42: P2 1人月 | L42: 通用
D43: 能量输出 | E43: 支持能量及能量密度结果输出 | F43: LMS Virtual Lab_Acoustic | G43: 7级 | H43: 2025年度 | I43: 2025.12 | J43: MxSim.Acoustic V2.0.0 | K43: P2 1人月 | L43: 通用
C45: 声场模块计划2023年9月起由新入学博士开始启动产品化工作，2024年度形成第一个版本，中间计划补充P2级别员工一人
H47: 2023年度 | K47: P1 6.5人月 P2 1人月
E48: 2024年度需开始界面开发工作，预期P1级别开发人员，6人月 | H48: 2024年度 | K48: P1 4人月 P2 15人月
H49: 2025年度 | K49: P2 9人月 P3 9人月

Sheet MxSim.Emag-电磁场产品基线
A1: L3 | B1: L4功能大类 | C1: L5功能子类 | D1: L6功能名称 （包含已有功能） | E1: 关键规格与描述 （如有可能，尽量定量指标描述） | F1: 对标软件 （具体到模块名，可为多个软件） | G1: 对标国外软件成熟度评价% （7级为基本满足日常使用需求，9级为成熟完全满足工程应用需求） 需要指出功能指标、功能差距 | H1: 规划年度 | I1: 基线达到时间（月） | J1: 隶属版本号 | K1: 预期人力成本（人月） （如：P1 2人月， P2 1人月） | L1: 行业/工业品需求分类 （通用类、XX行业/XX产品专用） | M1: 重难点评述
A2: 外部需求 | B2: 网格功能需求 | C2: 针对任务的特定网格功能需求 | D2: 自适应网格生成 | E2: 根据后验误差生成2D/3D自适应优化网格 | F2: Ansys Maxwell | G2: 7级 满足一般算例的自适应需求 | H2: 2023年度 | I2: 45139 | J2: MxSim.Emag V1.0.0 | K2: P1 2人月 | L2: 通用 | M2: 需要网格模块支撑
D3: 趋肤效应网格的自适应生成 | E3: 在金属表面，生成基于趋肤效应的三角形（二维）或四面体（三维）网格 | F3: Ansys Maxwell | G3: 7级 满足一般算例的计算需求 | H3: 2023年度 | I3: 45139 | J3: MxSim.Emag V1.0.0 | K3: P1 2人月 | L3: 通用
D4: 多部件网格一键生成 | E4: 用户可以设置一些网格尺寸的控制参数，如基于面最大单元长度、导体内部最大单元长度，基于控制参数自动生成多部件共节点网格 | F4: Ansys Maxwell、Comsol ACDC | G4: 7级 满足一般几何特征的零部件的网格生成 | H4: 2024年度 | I4: 45627 | J4: MxSim.Emag V2.0.0 | K4: P2 1人月 | L4: 通用
D5: 运动网格 | E5: 电磁场和结构场耦合时导致结构的运动网格需适时更新 | F5: Ansys Maxwell、Comsol ACDC | G5: 7级 对电机仿真需求的运动网格需求 | H5: 2026年度 | I5: 46357 | J5: MxSim.Emag V4.0.0 | K5: P2 2人月 | L5: 通用
A6: 低频电磁场求解器 | B6: 电磁材料库及材料属性自定义 | C6: 电场材料参数 | D6: 电导率 | E6: 各向同性 | F6: Ansys Maxwell | G6: 8级 | H6: 已有 | I6: / | J6: MxSim.Emag V1.0.0 | K6: / | L6: 通用
E7: 各向异性 | F7: Ansys Maxwell | G7: 8级 | H7: 已有 | I7: / | J7: MxSim.Emag V1.0.0 | K7: / | L7: 通用
E8: 恒电导率 | F8: Ansys Maxwell | G8: 8级 | H8: 已有 | I8: / | J8: MxSim.Emag V1.0.0 | K8: / | L8: 通用
E9: 非线性J-E曲线，仅支持3D直流分析 | F9: Ansys Maxwell | G9: 7级 | H9: 2024年度 | I9: 45413 | J9: MxSim.Emag V2.0.0 | K9: P2 1人月 | L9: 通用
E10: 随温度变化电导率 | F10: Ansys Maxwell | G10: 7级 | H10: 2024年度 | I10: 45627 | J10: MxSim.Emag V2.0.0 | K10: P2 1人月 | L10: 通用
D11: 介电常数 | E11: 各向同性 | F11: Ansys Maxwell | G11: 8级 | H11: 已有 | I11: / | J11: MxSim.Emag V1.0.0 | K11: / | L11: 通用
E12: 各向异性 | F12: Ansys Maxwell | G12: 8级 | H12: 2024年度 | I12: 45444 | J12: MxSim.Emag V2.0.0 | K12: P2 1人月 | L12: 通用
E13: 恒相对介电常数 | F13: Ansys Maxwell | G13: 8级 | H13: 已有 | I13: / | J13: MxSim.Emag V1.0.0 | K13: / | L13: 通用
E14: DE曲线 | F14: Ansys Maxwell | G14: 7级 | H14: 2024年度 | I14: 45444 | J14: MxSim.Emag V2.0.0 | K14: P2 1人月 | L14: 通用
D15: 损耗因子 | F15: Ansys Maxwell | G15: 7级 | H15: 2024年度 | I15: 45444 | J15: MxSim.Emag V2.0.0 | K15: P2 1人月 | L15: 通用
D16: 介电损耗切线 | E16: 设置该参数表示耗散高频电场功率的介电介质 | F16: Ansys Maxwell | G16: 7级 | H16: 2024年度 | I16: 45444 | J16: MxSim.Emag V2.0.0 | K16: P2 1人月 | L16: 通用
C17: 磁场材料参数 | D17: 磁导率 | E17: 各向同性 | F17: Ansys Maxwell | G17: 8级 | H17: 已有 | I17: / | J17: MxSim.Emag V1.0.0 | K17: / | L17: 通用
E18: 各向异性 | F18: Ansys Maxwell | G18: 8级 | H18: 已有 | I18: / | J18: MxSim.Emag V1.0.0 | K18: / | L18: 通用
E19: 恒磁导率 | F19: Ansys Maxwell | G19: 8级 | H19: 已有 | I19: / | J19: MxSim.Emag V1.0.0 | K19: / | L19: 通用
E20: BH曲线 | F20: Ansys Maxwell | G20: 7级 | H20: 2023年度 | I20: 45139 | J20: MxSim.Emag V1.0.0 | K20: P2 1人月 | L20: 通用
E21: 各向异性和BH曲线 | F21: Ansys Maxwell | G21: 7级 | H21: 2023年度 | I21: 45170 | J21: MxSim.Emag V1.0.0 | K21: P2 1人月 | L21: 通用
D22: 剩磁 | F22: Ansys Maxwell | G22: 7级 | H22: 2024年度 | I22: 45474 | J22: MxSim.Emag V2.0.0 | K22: P2 1人月 | L22: 通用
D23: 磁损耗切线 | E23: 要表示耗散高频磁场功率的铁氧体的磁性材料添加的属性 | F23: Ansys Maxwell | G23: 7级 | H23: 2024年度 | I23: 45474 | J23: MxSim.Emag V2.0.0 | K23: P2 1人月 | L23: 通用
D24: 矫顽力自定义 | E24: 支持对永磁材料的矫顽力进行自定义 | F24: Ansys Maxwell | G24: 7级 | H24: 2024年度 | I24: 45474 | J24: MxSim.Emag V2.0.0 | K24: P2 1人月 | L24: 通用
C25: 磁滞材料 | D25: 磁滞材料自定义 | E25: 对磁滞材料进行属性定义（2021年铁芯损耗这一模块取消了） | F25: Ansys Maxwell | G25: 7级 | H25: 2024年度 | I25: 45505 | J25: MxSim.Emag V2.0.0 | K25: P2 1人月 | L25: 通用
C26: 铁耗系数 | D26: 铁耗系数自定义 | E26: 基于铁耗三项式模型 ①直接定义材料铁耗系数； ②通过单频点或多频点BP曲线插值得到铁耗系数。 | F26: Ansys Maxwell | G26: 7级 | H26: 2023年度 | I26: 45231 | J26: MxSim.Emag V1.0.0 | K26: P2 1人月 | L26: 通用
C27: 常用材料库 | D27: 常用电磁材料库 | E27: 工程中常见材料模型库的建立，包括导电材料、绝缘材料、永磁材料、铁芯材料等 | F27: Ansys Maxwell | G27: 5级 添加基本电磁材料，丰富度需逐渐提升 | H27: 2024年度 | I27: 45536 | J27: MxSim.Emag V2.0.0 | K27: P1 3人月 | L27: 通用
C28: 永磁材料属性 | D28: 永磁材料参数定义 | E28: 用于电机电磁特性分析、应用于RMxprt | F28: Ansys Maxwell | G28: 7级 | H28: 2025年度 | I28: 45689 | J28: MxSim.Emag V3.0.0 | K28: P2 1人月 | L28: 通用
D29: 消磁曲线输入 | E29: 用于电机电磁特性分析、应用于RMxprt | F29: Ansys Maxwell | G29: 7级 | H29: 2025年度 | I29: 45689 | J29: MxSim.Emag V3.0.0 | K29: P2 1人月 | L29: 通用
C30: 部件定义 | D30: 叠片属性定义 | E30: 支持各个方向的叠片属性设置，坐标系支持直角、柱坐标、球坐标。 | F30: Ansys Maxwell | G30: 7级 现阶段支持部分坐标系，覆盖不全 | H30: 2023年度 | I30: 45170 | J30: MxSim.Emag V1.0.0 | K30: P2 1人月 | L30: 通用
D31: 利兹线（litz）定义 | E31: 仅支持瞬态、涡流绕组设置，用于减少高频绕组的交流损耗 | F31: Ansys Maxwell | G31: 7级 | H31: 2024年度 | I31: 45627 | J31: MxSim.Emag V2.0.0 | K31: P2 2人月 | L31: 通用
B32: 边界 | C32: 电磁场边界 | D32: 自然边界 | E32: 磁通量垂直于所定义边界 | F32: Ansys Maxwell | G32: 8级 | H32: 已有 | I32: / | J32: MxSim.Emag V1.0.0 | K32: / | L32: 通用
D33: 磁通量平行边界 | E33: 磁通量平行于所定义边界 | F33: Ansys Maxwell | G33: 8级 | H33: 2023年度 | I33: 45169 | J33: MxSim.Emag V1.0.0 | K33: P1 1人月 | L33: 通用
D34: 空气边界 | E34: 无穷远边界 | F34: Ansys Maxwell | G34: 7级 | H34: 2024年度 | I34: 45536 | J34: MxSim.Emag V2.0.0 | K34: P2 1人月 | L34: 通用
D35: 薄隙边界 | E35: 将两接触面定义为含一定气隙长度的边界，用于减小网格规模。 | F35: Ansys Maxwell | G35: 7级 | H35: 2024年度 | I35: 45627 | J35: MxSim.Emag V2.0.0 | K35: P3 2人月 | L35: 通用
D36: 阻抗边界 | E36: 阻抗边界是用来模拟薄介质层的边界条件，主要应用于谐态场分析。 | F36: Ansys Maxwell | G36: 7级 | H36: 2023年度 | I36: 45017 | J36: MxSim.Emag V1.0.0 | K36: P2 1人月 | L36: 通用
D37: 绝缘边界 | E37: 电场强度E在绝缘边界上是不连续的，可用于很薄的绝缘层。 | F37: Ansys Maxwell | G37: 7级 | H37: 2023年度 | I37: 45047 | J37: MxSim.Emag V1.0.0 | K37: P2 1人月 | L37: 通用
D38: 切向磁场强度边界 | E38: 模拟外加磁场，支持外加磁场恒定及随时间函数变化 | F38: Ansys Maxwell | G38: 7级 | H38: 已有 | I38: / | J38: MxSim.Emag V1.0.0 | K38: / | L38: 通用
D39: 对称边界 | E39: 对称边界条件是计算对称结构时采用的边界条件 | F39: Ansys Maxwell | G39: 8级 | H39: 已有 | I39: / | J39: MxSim.Emag V1.0.0 | K39: / | L39: 通用
D40: 周期对称边界 | E40: 周期边界条件是计算周期性对称结构时采用的边界条件，使主边界和从边界场量具有相同的幅度、相位和相同或相反的方向。支持旋转周期对称和平移周期对称。 | F40: Ansys Maxwell | G40: 8级 | H40: 已有 | I40: / | J40: MxSim.Emag V1.0.0 | K40: / | L40: 通用
B41: 激励 | C41: 电磁场激励 | D41: 电压源激励 | E41: 电压激励，支持以函数、列表、参数形式定义任意波形的电压 | F41: Ansys Maxwell | G41: 8级 | H41: 2023年度 | I41: 45078 | J41: MxSim.Emag V1.0.0 | K41: P2 1人月 | L41: 通用
D42: 电流源激励 | E42: 电流激励，支持以函数、列表、参数形式定义任意波形的电流 | F42: Ansys Maxwell | G42: 8级 | H42: 2023年度 | I42: 45078 | J42: MxSim.Emag V1.0.0 | L42: 通用
D43: 外部电路激励 | E43: 支持电路模块，包含常用电路元器件如电压源、电流源、开关、电阻、电容、电感、二极管，同时电磁场能够与电路进行场路耦合仿真 | F43: Ansys Maxwell | G43: 7级 二极管未添加 | H43: 已有 | I43: / | J43: MxSim.Emag V1.0.0 | K43: / | L43: 通用
D44: 涡流效应 | E44: 涡流场计算时，设置是否考虑线圈激励的涡流效应 | F44: Ansys Maxwell | G44: 7级 | H44: 2023年度 | I44: 45047 | J44: MxSim.Emag V1.0.0 | K44: P2 1人月 | L44: 通用
D45: 其他类型激励 | E45: 电荷激励、电流密度、电荷密度 | F45: Ansys Maxwell | G45: 8级 | H45: 已有 | I45: / | J45: MxSim.Emag V1.0.0 | K45: / | L45: 通用
E46: 其他类型的激励，如永磁激励，浮动导体，薄片导体等 | F46: Ansys Maxwell, Comsol ACDC | G46: 7级 | H46: 2023年度 | I46: 45078 | J46: MxSim.Emag V1.0.0 | K46: P2 1人月 | L46: 通用
B47: 分析类型 | C47: 磁场求解器 | D47: 2D静磁场求解器 | E47: 求解直流电流和永磁体引起的2D/3D静磁场问题，支持线性和非线性材料 | F47: Ansys Maxwell | G47: 8级 | H47: 2024年度 | I47: 45444 | J47: MxSim.Emag V2.0.0 | K47: P2 2人月 | L47: 通用
D48: 3D静磁场求解器 | F48: Ansys Maxwell | G48: 8级 | H48: 已有 | I48: / | J48: MxSim.Emag V1.0.0 | L48: 通用
D49: 2D涡流场求解器 | E49: 求解在频域中正弦变化的2D/3D磁场，支持线性和非线性材料，考虑位移电流，以及趋肤和邻近效应 | F49: Ansys Maxwell | G49: 8级 | H49: 2024年度 | I49: 45444 | J49: MxSim.Emag V2.0.0 | L49: 通用
D50: 3D涡流场求解器 | F50: Ansys Maxwell | G50: 8级 | H50: 已有 | I50: / | J50: MxSim.Emag V1.0.0 | L50: 通用
D51: 2D瞬态磁场求解器 | E51: 求解由时变激励、运动、以及线性或非线性材料中的永磁体引起的2D/3D瞬态磁场，考虑趋肤和邻近效应 | F51: Ansys Maxwell | G51: 8级 | H51: 2024年度 | I51: 45444 | J51: MxSim.Emag V2.0.0 | L51: 通用
D52: 3D瞬态磁场求解器 | F52: Ansys Maxwell | G52: 8级 | H52: 已有 | I52: / | J52: MxSim.Emag V1.0.0 | K52: / | L52: 通用
C53: 电场求解器 | D53: 2D静电场求解器 | E53: 求解线性材料中的2D静电场 | F53: Ansys Maxwell | G53: 8级 | H53: 2024年度 | I53: 45444 | J53: MxSim.Emag V2.0.0 | K53: P2 2人月 | L53: 通用
D54: 3D静电场求解器 | E54: 求解线性材料中的3D静电场 | F54: Ansys Maxwell | G54: 8级 | H54: 已有 | I54: / | J54: MxSim.Emag V1.0.0 | L54: 通用
D55: 2D交流传导场求解器 | E55: 求解在频域中正弦变化的2D电场 | F55: Ansys Maxwell | G55: 8级 | H55: 2024年度 | I55: 45444 | J55: MxSim.Emag V2.0.0 | L55: 通用
D56: 2D直流传导场求解器 | E56: 求解电压、电场和电势产生的2D电流密度 | F56: Ansys Maxwell | G56: 8级 | H56: 2024年度 | I56: 45444 | J56: MxSim.Emag V2.0.0 | L56: 通用
D57: 3D直流传导场求解器 | E57: 求解电压、电场和电势产生的3D电流密度 | F57: Ansys Maxwell | G57: 8级 | H57: 已有 | I57: / | J57: MxSim.Emag V1.0.0 | K57: / | L57: 通用
D58: 3D瞬态电场求解器 | E58: 求解非均匀材料中由时变电压、电荷分布或电流激发引起的瞬态电场 | F58: Ansys Maxwell | G58: 8级 | H58: 已有 | I58: / | J58: MxSim.Emag V1.0.0 | K58: / | L58: 通用
C59: 电路仿真（后续应独立） | D59: 直流、交流、瞬态 | E59: 电路模块独立出电磁场仿真，作为电磁场仿真接口引用 | F59: Ansys Maxwell | G59: 7级 具备基本的电路仿真功能，满足基本的电磁场对电路的需求，但界面未配套，电子元器件不够丰富 | H59: 已有 | I59: / | J59: MxSim.Emag V1.0.0 | K59: / | L59: 通用 | M59: 当前版本的电路功能支持范围有限，基本分析类型支持，元器件支持差距较大
B60: 分析方法 | C60: 有限元类方法 | D60: 节点有限元 | E60: 支持电场仿真部分 | F60: Ansys Maxwell | G60: 8级 | H60: 已有 | I60: / | J60: MxSim.Emag V1.0.0 | K60: / | L60: 通用
D61: 稳定节点积分 | E61: 低阶高精度单元 | F61: / | G61: / | H61: 已有 | I61: / | J61: MxSim.Emag V1.0.0 | K61: / | L61: 通用
D62: 边光滑有限元 | E62: 低阶高精度单元 | F62: / | G62: / | H62: 已有 | I62: / | J62: MxSim.Emag V1.0.0 | K62: / | L62: 通用
D63: 棱边元 | E63: 基于边的形函数进行磁场的计算，支持磁场分析，电场分析采用节点有限元法 | F63: Ansys Maxwell | G63: 7级 | H63: 2024年度 | I63: 45444 | J63: MxSim.Emag V2.0.0 | K63: P3 2人月 | L63: 通用
B64: 相关功能技术 | C64: 技术相关 | D64: 电磁自适应时间步法 | E64: 瞬态分析根据迭代误差自适应调整计算的时间步长 | F64: Ansys Maxwell | G64: 7级 | H64: 2023年度 | I64: 45261 | J64: MxSim.Emag V1.0.0 | K64: P2 1人月 | L64: 通用
C65: 功能相关 | D65: 全局参数设置 | E65: 设置全局参数，模型树中使用该参数变量代替值即可 | F65: Ansys Maxwell | G65: 7级 | H65: 2024年度 | I65: 45413 | J65: MxSim.Emag V2.0.0 | K65: P1 1人月 | L65: 通用 | M65: 界面配合
D66: 函数功能用户自定义 | E66: 函数表达式用户自定义 | F66: Ansys Maxwell | G66: 7级 | H66: 2024年度 | I66: 45413 | J66: MxSim.Emag V2.0.0 | L66: 通用
D67: 工程算例库 | E67: 针对某个分析建立工程算例库 | F67: Ansys Maxwell | G67: 5级 建立核心分析类型的算例库，复杂分析类型的模板库暂时不包含在此周期内 | H67: 2024年度 | I67: 45627 | J67: MxSim.Emag V2.0.0 | K67: P1 2人月 | L67: 通用
B68: 场路耦合 | C68: 场路耦合 | D68: 场路耦合分析 | E68: 能通过降价模型或瞬态协同仿真技术，实现场路协同设计，如实现电磁部件和系统设计同步 | F68: Ansys Maxwell/Simplorer | G68: 7级 | H68: 已有 | I68: / | J68: MxSim.Emag V1.0.0 | K68: / | L68: 通用 | M68: 具备基本流程，电路方面功能丰富性不足
D69: 外电路耦合 | E69: 电磁场与外电路的强耦合及迭代耦合 | F69: Ansys Maxwell | G69: 7级 | H69: 已有 | I69: / | J69: MxSim.Emag V1.0.0 | L69: 通用
B70: 仿真结果 | C70: 磁场结果 | D70: 矢量磁位 | E70: 矢量磁位云图输出 | F70: Ansys Maxwell | G70: 9级 | H70: 已有 | I70: / | J70: MxSim.Emag V1.0.0 | L70: 通用
D71: 磁场强度 | E71: 磁场强度云图输出 | F71: Ansys Maxwell | G71: 9级 | H71: 已有 | I71: / | J71: MxSim.Emag V1.0.0 | L71: 通用
D72: 磁通密度 | E72: 磁通密度云图输出 | F72: Ansys Maxwell | G72: 9级 | H72: 已有 | I72: / | J72: MxSim.Emag V1.0.0 | L72: 通用
D73: 场能量 | E73: 场能量云图输出 | F73: Ansys Maxwell | G73: 9级 | H73: 已有 | I73: / | J73: MxSim.Emag V1.0.0 | L73: 通用
D74: 损耗 | E74: 损耗云图输出 | F74: Ansys Maxwell | G74: 7级 | H74: 2023年度 | I74: 45200 | J74: MxSim.Emag V1.0.0 | K74: P1 2人月 | L74: 通用
D75: 场变量的镜像生成 | E75: 电磁场模型对称处理时，后处理输出可以将镜像云图显示出来 | F75: Ansys Maxwell | G75: 7级 | H75: 2023年度 | I75: 45200 | J75: MxSim.Emag V1.0.0 | L75: 通用 | M75: 需要后处理支持
C76: 电场结果 | D76: 标量电位 | E76: 标量电位云图输出 | F76: Ansys Maxwell | G76: 9级 | H76: 已有 | I76: / | J76: MxSim.Emag V1.0.0 | L76: 通用
D77: 电场强度 | E77: 电场强度云图输出 | F77: Ansys Maxwell | G77: 9级 | H77: 已有 | I77: / | J77: MxSim.Emag V1.0.0 | L77: 通用
D78: 电位移通量 | E78: 电位移云图输出 | F78: Ansys Maxwell | G78: 9级 | H78: 已有 | I78: / | J78: MxSim.Emag V1.0.0 | L78: 通用
D79: 面电荷密度 | E79: 面电荷密度云图输出 | F79: Ansys Maxwell | G79: 9级 | H79: 2023年度 | I79: 45200 | J79: MxSim.Emag V1.0.0 | L79: 通用
D80: 场变量的镜像生成 | E80: 电磁场模型对称处理时，后处理输出可以将镜像云图显示出来 | F80: Ansys Maxwell | G80: 7级 | H80: 2023年度 | I80: 45200 | J80: MxSim.Emag V1.0.0 | L80: 通用 | M80: 需要后处理支持
C81: 损耗计算 | D81: 涡流损耗 | F81: Ansys Maxwell | G81: 7级 | H81: 2023年度 | I81: 45261 | J81: MxSim.Emag V1.0.0 | K81: P2 1人月 | L81: 通用
D82: 铁心损耗 | E82: 绕组导体涡流损耗，铁心损耗为涡流损耗、磁滞损耗和其他损耗的和，三者有相关的经验公式 | F82: Ansys Maxwell | G82: 7级 | H82: 2023年度 | I82: 45261 | J82: MxSim.Emag V1.0.0 | K82: P2 1人月 | L82: 通用
C83: 衍生量计算 | D83: 力 | E83: Maxwell应力张量法，Lorentz法，虚位移法、节点力法 | F83: Ansys Maxwell | G83: 7级 部分场景力计算的精度仍有偏差 | H83: 已有 | I83: / | J83: MxSim.Emag V1.0.0 | K83: / | L83: 通用
D84: 力矩 | E84: 根据力和位移以及局部的坐标系计算其力矩 | F84: Ansys Maxwell | G84: 7级 | H84: 2023年度 | I84: 45200 | J84: MxSim.Emag V1.0.0 | K84: P2 1人月 | L84: 通用
D85: 能量 | E85: 电场能量、磁场能量、磁场共能量（coenergy）等 | F85: Ansys Maxwell | G85: 7级 | H85: 2023年度 | I85: 45231 | J85: MxSim.Emag V1.0.0 | L85: 通用 | M85: 后处理配合
C86: 曲线输出 | D86: 随时间的曲线输出 | E86: 自变量数据可来源衍生量、电磁计算器等计算结果，处理对象可以是点、线、面、体积等，场变量为各种场变量 | F86: Ansys Maxwell | G86: 8级 | H86: 2023年度 | I86: 45261 | J86: MxSim.Emag V1.0.0 | K86: P2 1人月 | L86: 通用 | M86: 需后处理配合
D87: 随频率的曲线输出 | E87: 自变量数据可来源衍生量、电磁计算器等计算结果，处理对象可以是点、线、面、体积等，场变量为各种场变量 | F87: Ansys Maxwell | G87: 8级 | H87: 2023年度 | I87: 45261 | J87: MxSim.Emag V1.0.0 | L87: 通用
C88: 云图输出逻辑 | D88: 场变量云图输出逻辑更改 | E88: 支持场变量不同部件的同时输出 | F88: Ansys Maxwell | G88: 7级 | H88: 2023年度 | I88: 45231 | J88: MxSim.Emag V1.0.0 | K88: P1 1人月 | L88: 通用 | M88: 需后处理配合
B89: 电机专用仿真模块 | C89: 电机仿真快速建模 | D89: 电机分析边界 | E89: 电机分析边界直观定义 | F89: Ansys Maxwell RMXprt | G89: 7级 | H89: 2024年度 | I89: 45627 | J89: MxSim.Emag V2.0.0 | K89: P2 2人月 | L89: 电机专用
D90: 电机分析载荷 | E90: 电机分析载荷直观定义 | F90: Ansys Maxwell RMXprt | G90: 7级 | H90: 2024年度 | I90: 45628 | J90: MxSim.Emag V2.0.0 | L90: 电机专用
D91: 电机绕组信息快速建模 | E91: 提供绕组的连接方式选择，自动创建最常用的外电路连接用于瞬态有限元分析 | F91: Ansys Maxwell RMXprt | G91: 7级 | H91: 2025年度 | I91: 45992 | J91: MxSim.Emag V3.0.0 | K91: P1 2人月 | L91: 电机
C92: 电机模型模板 （侧重电机模型建立） | D92: 通用旋转电机 | E92: 内转子感应机 | F92: Ansys Maxwell RMxprt | G92: 7级 | H92: 2025年度 | I92: 45992 | J92: MxSim.Emag V3.0.0 | K92: P1 6人月 P2 6人月 P3 2人月 | L92: 电机专用 | M92: 更加倾向于参数化建模
E93: 外转子感应机 | F93: Ansys Maxwell RMxprt | G93: 7级 | H93: 2025年度 | I93: 45992 | J93: MxSim.Emag V3.0.0 | L93: 电机专用
E94: 固体转子感应机 | F94: Ansys Maxwell RMxprt | G94: 7级 | H94: 2025年度 | I94: 45992 | J94: MxSim.Emag V3.0.0 | L94: 电机专用
E95: 缠绕转子感应机 | F95: Ansys Maxwell RMxprt | G95: 7级 | H95: 2025年度 | I95: 45992 | J95: MxSim.Emag V3.0.0 | L95: 电机专用
E96: 双馈感应发电机 | F96: Ansys Maxwell RMxprt | G96: 7级 | H96: 2025年度 | I96: 45992 | J96: MxSim.Emag V3.0.0 | L96: 电机专用
E97: 轴向通量感应机 | F97: Ansys Maxwell RMxprt | G97: 7级 | H97: 2025年度 | I97: 45992 | J97: MxSim.Emag V3.0.0 | L97: 电机专用
E98: 磁滞电机 | F98: Ansys Maxwell RMxprt | G98: 7级 | H98: 2025年度 | I98: 45992 | J98: MxSim.Emag V3.0.0 | L98: 电机专用
E99: 旋转场同步机 | F99: Ansys Maxwell RMxprt | G99: 7级 | H99: 2025年度 | I99: 45992 | J99: MxSim.Emag V3.0.0 | L99: 电机专用
E100: 旋转电枢同步机 | F100: Ansys Maxwell RMxprt | G100: 7级 | H100: 2025年度 | I100: 45992 | J100: MxSim.Emag V3.0.0 | L100: 电机专用
...

Sheet 版本历史记录
A1: 版本号 | B1: 版本说明 | C1: 修订日期 | D1: 修订说明
D2: 例子XX产品总计XX元，其中P1 XX天，合计XXX元，P2 XX天，合计XXX元；P3 XX天，合计XXX元；1、典型设备及管道智能化分析软件研发项目V0.0.2中《1.建立典型设备和管道样本数据库，2.提取特征参数，3.构建适用于典型设备和管道智能预测及设计优化的代理模型4.开发典型设备和管道智能化分析软件建立典型设备和管道样本数据库》任务与典型设备及管道智能化分析软件研发项目V0.0.3《确认系统设计方案；搭建系统框架；搭建数据库；页面可增删改任务》重复，重复的工时是支撑MxDesign.NodeFlow V1.0.1项目中《1.解决软件运行中的warning；2.求解器节点求解过程中处于未响应状态，影响使用体验；3.除MxSim外的商软，求解速度优化》任务，经排查，工时多预计39天 2、典型设备及管道智能化分析软件研发项目V0.0.2中龙旺的《提供3种以上试验设计算法，并进行试验设计分析，实现仿真模型复杂高维设计域内试验设计方案的快速生成。》21天工作量没有做，进行删除

Sheet 产品工作难度评估
N1: 评级或向下 | O1: 1 | P1: 1
L2: P3-P4 | M2: P2-P3 | N2: P1-P2 | O2: 2 | P2: 1.1
M3: P2-P4 | N3: P1-P3 | O3: 3 | P3: 1.2
N4: P1-P4 | O4: 4 | P4: 1.3
B6: 产品 | C6: 难度等级 | D6: 难度等级个数 | E6: 折算后的个数 | G6: 产品 | H6: 难度等级 | I6: 难度等级个数 | J6: 折算后的个数
B7: NodeFlow | C7: 1 | D7: =COUNTIF('2026Q1'!#REF!,1) -> #REF! | E7: =D7*$P$1 -> #REF! | G7: Wizard | H7: 1 | I7: =COUNTIF(#REF!,1) -> #REF! | J7: =I7*$P$1 -> #REF!
C8: 2 | D8: =COUNTIF('2026Q1'!#REF!,2) -> #REF! | E8: =D8*$P$2 -> #REF! | H8: 2 | I8: =COUNTIF(#REF!,2) -> #REF! | J8: =I8*$P$2 -> #REF!
C9: 3 | D9: =COUNTIF('2026Q1'!#REF!,3) -> #REF! | E9: =D9*$P$3 -> #REF! | H9: 3 | I9: =COUNTIF(#REF!,3) -> #REF! | J9: =I9*$P$3 -> #REF!
C10: 4 | D10: =COUNTIF('2026Q1'!#REF!,4) -> #REF! | E10: =D10*$P$4 -> #REF! | H10: 4 | I10: =COUNTIF(#REF!,4) -> #REF! | J10: =I10*$P$4 -> #REF!
B11: 总计 | D11: =SUM(D7:D10) -> #REF! | E11: =SUM(E7:E10) -> #REF! | G11: 总计 | I11: =SUM(I7:I10) -> #REF! | J11: =SUM(J7:J10) -> #REF!
B12: 总体难度比例 | D12: =(E11+J11)/(D11+I11) -> #REF!

Sheet 2026Q1
W1: 评级或向下 | Z1: 1 | AA1: 1
D2: 产品 | E2: MxDesign | W2: P3-P4 | X2: P2-P3 | Y2: P1-P2 | Z2: 2 | AA2: 1.1
D3: 负责人 | E3: 廖孟亮 | X3: P2-P4 | Y3: P1-P3 | Z3: 3 | AA3: 1.2
D4: 开始 时间 | E4: 45383 | Y4: P1-P4 | Z4: 4 | AA4: 1.3
A5: 需求来源 | B5: 需求优先级 | C5: 是否为产品需求 | D5: *客户来源 | E5: *L4功能大类 | F5: *L5功能子类 | G5: *当前基线 | H5: *L6功能名称（需开发项） | I5: *关键规格与描述 | J5: *验收标准（对应交付物是什么） | K5: *对标软件 | L5: *是否需要技服制作自测算例 | M5: *是否需要技服制作算例 | N5: *是否需要进行迭代测试 | O5: *成熟度评价% | P5: *责任人 | Q5: 人员实际等级 | R5: *任务等级 | S5: 实际等级数据处理 | T5: 任务等级数据处理 | U5: 基数 | V5: *规划年度 | W5: *基线达到时间 | X5: *隶属版本号 | Y5: *预期人力成本（人天） | AE5: *开始时间 | AF5: *预计结束时间 | AG5: 考虑难度系数人力成本（人天） | AM5: 按任务等级计算费用 | AP5: 需求ID | AQ5: 任务ID | AR5: 人天 | AS5: 工时 | AT5: 备注
Y6: SX | Z6: P1 | AA6: P2 | AB6: P3 | AC6: P4 | AD6: P5 | AG6: SX | AH6: P1 | AI6: P2 | AJ6: P3 | AK6: P4 | AL6: P5
A7: 公司关联产品需求 | B7: 中 | C7: 否 | D7: 前后处理平台-自研 | E7: MxSim | F7: 产品管理 | H7: 产品及项目整体架构管理 | I7: 1.管理MxSim.GUI相关产品及项目。 2.管理MxSim.CAD&CG相关产品及项目。 3.部门内部相关制度文档材料制作。 4.协调沟通部门开发、测试对接工作。 6.指导振华重工、电机参数化建模项目开发。 | J7: 无 | K7: 无 | L7: 否 | M7: 否 | N7: 否 | O7: 无 | P7: 汤光泽 | Q7: P4 | R7: P4 | V7: 2026 | W7: 46112 | X7: MxSim.GUI-通用-V3.0.0 | AC7: 72 | AE7: 46023 | AF7: 46112 | AP7: 8240 | AQ7: 19936 | AR7: =SUM(Y7:AD7) -> 72 | AS7: =AR7*8 -> 576
A8: 公司关联产品需求 | B8: 中 | C8: 否 | D8: 前后处理平台-自研 | E8: MxSim | F8: 产品管理 | H8: 产品及项目整体架构管理 | I8: 1.管理MxSim.GUI相关产品及项目。 2.管理MxSim.CAD&CG相关产品及项目。 3.部门内部相关制度文档材料制作。 4.协调沟通部门开发、测试对接工作。 6.指导振华重工、电机参数化建模项目开发。 | J8: 无 | K8: 无 | L8: 否 | M8: 否 | N8: 否 | O8: 无 | P8: 王飞奇 | Q8: P1 | R8: P1 | V8: 2026 | W8: 46112 | X8: MxSim.GUI-通用-V3.0.0 | Z8: 72 | AE8: 46023 | AF8: 46112 | AP8: 8240 | AQ8: 19937 | AR8: =SUM(Y8:AD8) -> 72 | AS8: =AR8*8 -> 576
A9: 公司关联产品需求 | B9: 高 | C9: 是 | D9: 通用结构平台-自研 | E9: MxSim.Mech | F9: CAD | G9: 当前版本不支持草图模式 | H9: 当前版本不支持草图创建功能 | I9: 开发草图基础图元：点、线段、多段线、圆心－半径画圆、椭圆弧、样条曲线、圆上三点画圆、圆心－起点－终点画弧、圆上三点画弧、椭圆，复合图元：矩形、平行四边形、正多边形创建功能 | J9: 点击草图模式后再点击各个草图图标即可创建各类二维几何草图 | K9: spaceclaim | L9: 否 | M9: 否 | N9: 是 | O9: 5级 | P9: 吴维煜 | Q9: P2 | R9: P2 | S9: 1 | T9: 2 | U9: 2 | V9: 2026 | W9: 46112 | X9: MxSim.Mechanical-通用-GUI-V3.0.0 | AA9: 15 | AE9: 46023 | AF9: 46112 | AP9: 8213 | AQ9: 19993 | AR9: =SUM(Y9:AD9) -> 15 | AS9: =AR9*8 -> 120
A10: 公司关联产品需求 | B10: 中 | C10: 是 | D10: 多物理场与智算平台-自研 | E10: MxSim.Motor | F10: GUI | H10: 斜槽斜极分析和非斜槽斜极分析的后处理切片与全周期模型及矢量箭头、等值线联动 | I10: 1、非斜槽斜极分析，后处理切片实现全周期模型，并且该全周期模型支持矢量箭头和等值线功能； 2、斜槽斜极分析，后处理的每个切片及所有切片实现全周期模型，并且该全周期模型支持矢量箭头和等值线功能； 3、全周期模型需匹配正周期和反周期模型 | J10: 验证标准：【无需算例，直接通过软件进行创建】 验证算例例子：【无需算例，直接进行软件测试】 | K10: Maxwell | L10: 否 | M10: 否 | N10: 是 | O10: 5级 | P10: 曹业鸿 | Q10: P0 | R10: P2 | V10: 2026 | W10: 46112 | X10: MxSim.Motor电机综合智能仿真分析软件-GUI-V2.0.0 | Y10: 5 | AE10: 46023 | AF10: 46112 | AP10: 8242 | AQ10: 20024 | AR10: =SUM(Y10:AD10) -> 5 | AS10: =AR10*8 -> 40
A11: 公司关联产品需求 | B11: 中 | C11: 是 | D11: 多物理场与智算平台-自研 | E11: MxSim.Motor | F11: GUI | H11: 同一工况下的所有云图的时间步需要同步 | I11: 1、某一云图运行到了一定时间步后，与该云图所处的同一工况的所有云图，均需切换相同时间步，与之不同则无需改变 | J11: 验证标准：【无需算例，直接通过软件进行创建】 验证算例例子：【无需算例，直接进行软件测试】 | K11: Maxwell | L11: 否 | M11: 否 | N11: 是 | O11: 5级 | P11: 曹业鸿 | Q11: P0 | R11: P2 | V11: 2026 | W11: 46112 | X11: MxSim.Motor电机综合智能仿真分析软件-GUI-V2.0.0 | Y11: 5 | AE11: 46023 | AF11: 46112 | AP11: 8243 | AQ11: 20025 | AR11: =SUM(Y11:AD11) -> 5 | AS11: =AR11*8 -> 40
A12: 公司关联产品需求 | B12: 中 | C12: 是 | D12: 多物理场与智算平台-自研 | E12: MxSim.Motor | F12: GUI | H12: 材料温度相关性配置 | I12: 根据材料温度相关性进行设置部件温度 | J12: 验证标准：【无需算例，直接通过软件进行创建】 验证算例例子：【无需算例，直接进行软件测试】 | K12: Maxwell | L12: 否 | M12: 否 | N12: 是 | O12: 5级 | P12: 曹业鸿 | Q12: P0 | R12: P2 | V12: 2026 | W12: 46112 | X12: MxSim.Motor电机综合智能仿真分析软件-GUI-V2.0.0 | Y12: 1 | AE12: 46023 | AF12: 46112 | AP12: 8244 | AQ12: 20026 | AR12: =SUM(Y12:AD12) -> 1 | AS12: =AR12*8 -> 8
A13: 公司关联产品需求 | B13: 中 | C13: 是 | D13: 多物理场与智算平台-自研 | E13: MxSim.Motor | F13: GUI | H13: 磁矢量位边界需求设置 | I13: 磁矢量位针对不同分析工况输入设置和关键字设置：瞬态分析和静态分析，保留原先磁矢量位不作处理，关键字输出也不作处理；频域分析：需要在值的基础上添加个相位参数 | J13: 验证标准：【无需算例，直接通过软件进行创建】 验证算例例子：【无需算例，直接进行软件测试】 | K13: Maxwell | L13: 否 | M13: 否 | N13: 是 | O13: 5级 | P13: 曹业鸿 | Q13: P0 | R13: P2 | V13: 2026 | W13: 46112 | X13: MxSim.Motor电机综合智能仿真分析软件-GUI-V2.0.0 | Y13: 1 | AE13: 46023 | AF13: 46112 | AP13: 8245 | AQ13: 20027 | AR13: =SUM(Y13:AD13) -> 1 | AS13: =AR13*8 -> 8
A14: 公司关联产品需求 | B14: 中 | C14: 是 | D14: 多物理场与智算平台-自研 | E14: MxSim.Motor | F14: GUI | H14: 电机端部电阻电感计算 | I14: 电机参数化建模生成电磁性能分析时，对于需要填充绕组电阻和电感的区域进行函数调用计算，将返回的结果填充到对应位置 | J14: 验证标准：【无需算例，直接通过软件进行创建】 验证算例例子：【无需算例，直接进行软件测试】 | K14: Maxwell | L14: 否 | M14: 否 | N14: 是 | O14: 5级 | P14: 曹业鸿 | Q14: P0 | R14: P2 | V14: 2026 | W14: 46112 | X14: MxSim.Motor电机综合智能仿真分析软件-GUI-V2.0.0 | Y14: 2 | AE14: 46023 | AF14: 46112 | AP14: 8246 | AQ14: 20028 | AR14: =SUM(Y14:AD14) -> 2 | AS14: =AR14*8 -> 16
A15: 公司关联产品需求 | B15: 中 | C15: 是 | D15: 多物理场与智算平台-自研 | E15: MxSim.Motor | F15: GUI | H15: 静态_似稳电磁场分析气隙处共节点网格需求 | I15: 静态分析和频域分析，不存在运动边界，气隙处的网格均保证共节点，即保证所有边界是共拓扑； 瞬态分析时，气隙几何处要保证非共拓扑，即瞬态要保证气隙处不共节点； | J15: 验证标准：【无需算例，直接通过软件进行创建】 验证算例例子：【无需算例，直接进行软件测试】 | K15: Maxwell | L15: 否 | M15: 否 | N15: 是 | O15: 5级 | P15: 曹业鸿 | Q15: P0 | R15: P2 | V15: 2026 | W15: 46112 | X15: MxSim.Motor电机综合智能仿真分析软件-GUI-V2.0.0 | Y15: 2 | AE15: 46023 | AF15: 46112 | AP15: 8247 | AQ15: 20029 | AR15: =SUM(Y15:AD15) -> 2 | AS15: =AR15*8 -> 16
A16: 公司关联产品需求 | B16: 中 | C16: 是 | D16: 多物理场与智算平台-自研 | E16: MxSim.Motor | F16: GUI | H16: 绕组需求对齐设置 | I16: 兼容三相电机的静磁、频域分析和瞬态分析的绕组需求 | J16: 验证标准：【无需算例，直接通过软件进行创建】 验证算例例子：【无需算例，直接进行软件测试】 | K16: Maxwell | L16: 否 | M16: 否 | N16: 是 | O16: 5级 | P16: 曹业鸿 | Q16: P0 | R16: P2 | V16: 2026 | W16: 46112 | X16: MxSim.Motor电机综合智能仿真分析软件-GUI-V2.0.0 | Y16: 3 | AE16: 46023 | AF16: 46112 | AP16: 8248 | AQ16: 20030 | AR16: =SUM(Y16:AD16) -> 3 | AS16: =AR16*8 -> 24
A17: 公司关联产品需求 | B17: 中 | C17: 是 | D17: 多物理场与智算平台-自研 | E17: MxSim.Motor | F17: GUI | H17: 气隙几何需求 | I17: 基于现有模型，在构建气隙的时候，根据定转子及其类型，进行分割模型 | J17: 验证标准：【无需算例，直接通过软件进行创建】 验证算例例子：【无需算例，直接进行软件测试】 | K17: Maxwell | L17: 否 | M17: 否 | N17: 是 | O17: 5级 | P17: 曹业鸿 | Q17: P0 | R17: P2 | V17: 2026 | W17: 46112 | X17: MxSim.Motor电机综合智能仿真分析软件-GUI-V2.0.0 | Y17: 3 | AE17: 46023 | AF17: 46112 | AP17: 8249 | AQ17: 20031 | AR17: =SUM(Y17:AD17) -> 3 | AS17: =AR17*8 -> 24
A18: 公司关联产品需求 | B18: 中 | C18: 是 | D18: 多物理场与智算平台-自研 | E18: MxSim.Motor | F18: GUI | H18: 气隙曲线绘制 | I18: 支持绘制气隙磁密 、气隙径向磁密 、气隙切向磁密、气隙电磁力密、气隙径向电磁力密、气隙切向电磁力密曲线 | J18: 验证标准：【无需算例，直接通过软件进行创建】 验证算例例子：【无需算例，直接进行软件测试】 | K18: Maxwell | L18: 否 | M18: 否 | N18: 是 | O18: 5级 | P18: 曹业鸿 | Q18: P0 | R18: P2 | V18: 2026 | W18: 46112 | X18: MxSim.Motor电机综合智能仿真分析软件-GUI-V2.0.0 | Y18: 3 | AE18: 46023 | AF18: 46112 | AP18: 8250 | AQ18: 20032 | AR18: =SUM(Y18:AD18) -> 3 | AS18: =AR18*8 -> 24
A19: 公司关联产品需求 | B19: 中 | C19: 是 | D19: 多物理场与智算平台-自研 | E19: MxSim.Motor | F19: GUI | H19: 平行齿功能 | I19: 参数化建模支持构建槽型的平行齿功能，并修改相应参数化建模界面 | J19: 验证标准：【无需算例，直接通过软件进行创建】 验证算例例子：【无需算例，直接进行软件测试】 | K19: Maxwell | L19: 否 | M19: 否 | N19: 是 | O19: 5级 | P19: 曹业鸿 | Q19: P0 | R19: P2 | V19: 2026 | W19: 46112 | X19: MxSim.Motor电机综合智能仿真分析软件-GUI-V2.0.0 | Y19: 4 | AE19: 46023 | AF19: 46112 | AP19: 8251 | AQ19: 20033 | AR19: =SUM(Y19:AD19) -> 4 | AS19: =AR19*8 -> 32
A20: 公司关联产品需求 | B20: 中 | C20: 是 | D20: 多物理场与智算平台-自研 | E20: MxSim.Motor | F20: GUI | H20: 瞬态分析指定场变量输出帧数 | I20: 制作电机瞬态输出控制面板，支持三种类型的指定输出 ，适配关键字输出 | J20: 验证标准：【无需算例，直接通过软件进行创建】 验证算例例子：【无需算例，直接进行软件测试】 | K20: Maxwell | L20: 否 | M20: 否 | N20: 是 | O20: 5级 | P20: 曹业鸿 | Q20: P0 | R20: P2 | V20: 2026 | W20: 46112 | X20: MxSim.Motor电机综合智能仿真分析软件-GUI-V2.0.0 | Y20: 1 | AE20: 46023 | AF20: 46112 | AP20: 8252 | AQ20: 20034 | AR20: =SUM(Y20:AD20) -> 1 | AS20: =AR20*8 -> 8
A21: 公司关联产品需求 | B21: 中 | C21: 是 | D21: 多物理场与智算平台-自研 | E21: MxSim.Motor | F21: GUI | H21: 完成电机前处理及参数化建模产品手册 | I21: 1、产品手册文档 | J21: 验证标准：【无需算例，直接通过软件进行创建】 验证算例例子：【无需算例，直接进行软件测试】 | K21: Maxwell | L21: 否 | M21: 否 | N21: 是 | O21: 5级 | P21: 曹业鸿 | Q21: P0 | R21: P2 | V21: 2026 | W21: 46112 | X21: MxSim.Motor电机综合智能仿真分析软件-GUI-V2.0.0 | Y21: 3 | AE21: 46023 | AF21: 46112 | AP21: 8253 | AQ21: 20035 | AR21: =SUM(Y21:AD21) -> 3 | AS21: =AR21*8 -> 24
... A23: 公司关联产品需求 | B23: 中 | C23: 是 | D23: 多物理场与智算平台-自研 | E23: MxSim.Motor | F23: GUI | H23: 界面架构优化 | I23: 修改Motor底层架构与Mech持平，并实现Motor现有功能 | J23: 验证标准：【无需算例，直接通过软件进行创建】 验证算例例子：【无需算例，直接进行软件测试】 | K23: Maxwell | L23: 否 | M23: 否 | N23: 是 | O23: 5级 | P23: 曹业鸿 | Q23: P0 | R23: P2 | V23: 2026 | W23: 46112 | X23: MxSim.Motor电机综合智能仿真分析软件-GUI-V2.0.0 | Y23: 28 | AE23: 46023 | AF23: 46112 | AP23: 8255 | AQ23: 20037 | AR23: =SUM(Y23:AD23) -> 28 | AS23: =AR23*8 -> 224
A24: 公司关联产品需求 | B24: 高 | C24: 是 | D24: 多物理场与智算平台-自研 | E24: MxSim.Motor | F24: GUI | H24: 界面功能扩展，界面美观优化，菜单栏、工具栏、快捷操作、几何拾取逻辑扩展、工程文件保存 | I24: /需要进一步细化 | J24: 验证标准：【无需算例，直接通过软件进行创建】 验证算例例子：【无需算例，直接进行软件测试】 | K24: Ansys Electronic | L24: 否 | M24: 否 | N24: 是 | O24: 5级 | P24: 刘奉明 | Q24: P1 | R24: P1 | S24: 0 | T24: 1 | U24: 0 | V24: 2026 | W24: 46112 | X24: MxSim.Motor电机综合智能仿真分析软件-GUI-V2.0.0 | Z24: 25 | AE24: 46023 | AF24: 46112 | AP24: 8256 | AQ24: 20038 | AR24: =SUM(Y24:AD24) -> 25 | AS24: =AR24*8 -> 200
A25: 公司关联产品需求 | B25: 高 | C25: 是 | D25: 多物理场与智算平台-自研 | E25: MxSim.Motor | F25: GUI | H25: 界面底层架构优化 | I25: /需要进一步细化 | J25: 验证标准：【无需算例，直接通过软件进行创建】 验证算例例子：【无需算例，直接进行软件测试】 | K25: Ansys Electronic | L25: 否 | M25: 否 | N25: 是 | O25: 5级 | P25: 刘奉明 | Q25: P1 | R25: P1 | S25: 0 | T25: 1 | U25: 0 | V25: 2026 | W25: 46112 | X25: MxSim.Motor电机综合智能仿真分析软件-GUI-V2.0.0 | Z25: 30 | AE25: 46023 | AF25: 46112 | AP25: 8257 | AQ25: 20039 | AR25: =SUM(Y25:AD25) -> 30 | AS25: =AR25*8 -> 240
A26: 公司关联产品需求 | B26: 高 | C26: 是 | D26: 多物理场与智算平台-自研 | E26: MxSim.Motor | F26: GUI | H26: 分析工况显示需求 | I26: /需要进一步细化 | J26: 验证标准：【无需算例，直接通过软件进行创建】 验证算例例子：【无需算例，直接进行软件测试】 | K26: Ansys Electronic | L26: 否 | M26: 否 | N26: 是 | O26: 5级 | P26: 刘奉明 | Q26: P1 | R26: P1 | S26: 0 | T26: 1 | U26: 0 | V26: 2026 | W26: 46112 | X26: MxSim.Motor电机综合智能仿真分析软件-GUI-V2.0.0 | Z26: 2 | AE26: 46023 | AF26: 46112 | AP26: 8258 | AQ26: 20040 | AR26: =SUM(Y26:AD26) -> 2 | AS26: =AR26*8 -> 16
A27: 公司关联产品需求 | B27: 高 | C27: 是 | D27: 多物理场与智算平台-自研 | E27: MxSim.Motor | F27: GUI | H27: 非线性迭代步数设置 | I27: /需要进一步细化 | J27: 验证标准：【无需算例，直接通过软件进行创建】 验证算例例子：【无需算例，直接进行软件测试】 | K27: Ansys Electronic | L27: 否 | M27: 否 | N27: 是 | O27: 5级 | P27: 刘奉明 | Q27: P1 | R27: P1 | S27: 0 | T27: 1 | U27: 0 | V27: 2026 | W27: 46112 | X27: MxSim.Motor电机综合智能仿真分析软件-GUI-V2.0.0 | Z27: 1 | AE27: 46023 | AF27: 46112 | AP27: 8259 | AQ27: 20041 | AR27: =SUM(Y27:AD27) -> 1 | AS27: =AR27*8 -> 8
A28: 公司关联产品需求 | B28: 高 | C28: 是 | D28: 多物理场与智算平台-自研 | E28: MxSim.Motor | F28: GUI | H28: 后处理多帧数据导入优化 | I28: /需要进一步细化 | J28: 验证标准：【无需算例，直接通过软件进行创建】 验证算例例子：【无需算例，直接进行软件测试】 | K28: Ansys Electronic | L28: 否 | M28: 否 | N28: 是 | O28: 5级 | P28: 刘奉明 | Q28: P1 | R28: P1 | V28: 2026 | W28: 46112 | X28: MxSim.Motor电机综合智能仿真分析软件-GUI-V2.0.0 | Z28: 1 | AE28: 46023 | AF28: 46112 | AP28: 8260 | AQ28: 20042 | AR28: =SUM(Y28:AD28) -> 1 | AS28: =AR28*8 -> 8
A29: 公司关联产品需求 | B29: 高 | C29: 是 | D29: 多物理场与智算平台-自研 | E29: MxSim.Motor | F29: GUI | H29: 完成电机后处理产品手册 | I29: /需要进一步细化 | J29: 1、产品手册文档 | K29: Ansys Electronic | L29: 否 | M29: 否 | N29: 是 | O29: 5级 | P29: 刘奉明 | Q29: P1 | R29: P1 | V29: 2026 | W29: 46112 | X29: MxSim.Motor电机综合智能仿真分析软件-GUI-V2.0.0 | Z29: 2 | AE29: 46023 | AF29: 46112 | AP29: 8261 | AQ29: 20043 | AR29: =SUM(Y29:AD29) -> 2 | AS29: =AR29*8 -> 16
A30: 公司关联产品需求 | B30: 高 | C30: 是 | D30: 多物理场与智算平台-自研 | E30: MxSim.Motor | F30: GUI | H30: 后处理切帧导入功能 | I30: /需要进一步细化 | J30: 验证标准：【无需算例，直接通过软件进行创建】 验证算例例子：【无需算例，直接进行软件测试】 | K30: Ansys Electronic | L30: 否 | M30: 否 | N30: 是 | O30: 5级 | P30: 刘奉明 | Q30: P1 | R30: P1 | V30: 2026 | W30: 46112 | X30: MxSim.Motor电机综合智能仿真分析软件-GUI-V2.0.0 | Z30: 5 | AE30: 46023 | AF30: 46112 | AP30: 8262 | AQ30: 20044 | AR30: =SUM(Y30:AD30) -> 5 | AS30: =AR30*8 -> 40
A31: 公司关联产品需求 | B31: 高 | C31: 是 | D31: 通用结构平台-自研 | E31: MxSim.Mech | F31: Mesh | G31: 当前版本不支持复杂工程模型的单部件四面体网格生成 | H31: 复杂工程模型的单部件四面体网格生成 | I31: 具备对复杂工程模型的单部件四面体并行剖分 | J31: 软件支持对复杂工程模型的并行四面体网格生成，且剖分速度能达到Hypermesh的75%。 1.打开软件，导入几何模型，进行四面体剖分，能完成四面体网格生成，剖分的时间小于相同尺寸下Hypermesh剖分时间的75%则验收通过。 2.使用已有几何文件测试算例，无需技术服务部及测试部额外制作算例。 | K31: Hypermesh | L31: 否 | M31: 否 | N31: 是 | O31: 7级 | P31: 王海东 | Q31: P1 | R31: P2 | T31: 2 | V31: 2026 | W31: 46112 | X31: MxSim.Mechanical-通用-GUI-V3.0.0 | Z31: 35 | AE31: 46023 | AF31: 46112 | AP31: 8215 | AQ31: 19995 | AR31: =SUM(Y31:AD31) -> 35 | AS31: =AR31*8 -> 280
A32: 公司关联产品需求 | B32: 高 | C32: 是 | D32: 通用结构平台-自研 | E32: MxSim.Mech | F32: Mesh | G32: 当前版本不支持基于距离场控制的初始网格基于距离场控制的初始网格细化细化 | H32: 基于距离场控制的初始网格基于距离场控制的初始网格细化细化 | I32: 具备基于距离场控制三角形、四面体初始网格加点细化 | J32: 软件支持基于距离场控制三角形、四面体初始网格加点细化。 1. 打开软件，导入几何模型，进行三角形或四面体剖分，能正常进行网格生成。 2.使用已有几何文件测试算例，无需技术服务部及测试部额外制作算例。 | K32: 无 | L32: 否 | M32: 否 | N32: 是 | O32: 7级 | P32: 王海东 | Q32: P1 | R32: P2 | T32: 2 | V32: 2026 | W32: 46112 | X32: MxSim.Mechanical-通用-GUI-V3.0.0 | Z32: 20 | AE32: 46023 | AF32: 46112 | AP32: 8216 | AQ32: 19996 | AR32: =SUM(Y32:AD32) -> 20 | AS32: =AR32*8 -> 160
A33: 公司关联产品需求 | B33: 高 | C33: 是 | D33: 通用结构平台-自研 | E33: MxSim.Motor | F33: Mesh | G33: 当前界面重构版本不支持电机模块网格共节点 | H33: 界面重构版本电机模块网格共节点集成 | I33: 界面重构版本电机模块具备网格共节点 | J33: 界面重构版本电机模块支持二维电机剖分的网格共节点。 1.打开软件，建立电机模型，剖分网格，生成的网格在边界上保证共节点。 2.使用已有几何文件测试算例，无需技术服务部及测试部额外制作算例。 | K33: 无 | L33: 否 | M33: 否 | N33: 是 | O33: 7级 | P33: 王海东 | Q33: P1 | R33: P1 | T33: 1 | V33: 2026 | W33: 46112 | X33: MxSim.Motor电机综合智能仿真分析软件-GUI-V2.0.0 | Z33: 11 | AE33: 46023 | AF33: 46112 | AP33: 8287 | AQ33: 20051 | AR33: =SUM(Y33:AD33) -> 11 | AS33: =AR33*8 -> 88
A34: 公司关联产品需求 | B34: 高 | C34: 是 | D34: 通用结构平台-自研 | E34: MxSim.Mech | F34: Mesh | G34: 当前版本不支持封闭几何模型的均匀六面体网格网格生成（保持曲面特征） | H34: 当前版本不支持封闭几何模型的均匀六面体网格网格生成（保持曲面特征） | I34: 具备对于任意几何模型的均匀六面体网格生成（保持曲面特征） | J34: 支持输入尺寸对封闭几何体进行六面体网格生成（保持曲面特征），生成的六面体网格与给定的几何模型之间的 豪斯多夫距离小于1%。 1. 打开软件，选择测试模型进行导入，根据给定尺寸生成内部均匀的六面体网格生成（保持曲面特征）。 2. 使用已有几何文件测试算例，无需技术服务部及测试部额外制作算例。 | K34: 无 | L34: 否 | M34: 否 | N34: 否 | O34: 7级 | P34: 殷思麒 | Q34: P1 | R34: P1 | T34: =SUBSTITUTE(R34,"P","") -> 1 | V34: 2026 | W34: 46112 | X34: MxSim.Mechanical-通用-GUI-V3.0.0 | Z34: 6 | AE34: 46023 | AF34: 46112 | AP34: 8218 | AQ34: 19997 | AR34: =SUM(Y34:AD34) -> 6 | AS34: =AR34*8 -> 48
A35: 公司关联产品需求 | B35: 高 | C35: 是 | D35: 通用结构平台-自研 | E35: MxSim.Mech | F35: Mesh | G35: 当前MxSim.GUI.3.0版本只支持部分网格功能模块 | H35: 网格自定义剖分模块、网格变换模块、网格质量检测模块、网格手动生成模块、网格信息统计模块、网格重剖分模块、网格文件导出模块。 | I35: 网格自定义剖分模块：支持拾取线、面、体创建包围盒\球进行自定义区域加密；支持创建包围盒\球\圆柱进行自定义区域加密； 网格变换模块：支持对网格进行旋转、平移、镜像、阵列变换操作； 网格质量检测模块：支持1D 2D 3D 网格进行质量检测； 网格手动生成模块： 支持网格通过拉伸、扫掠等手动生成； 网格信息统计模块：支持统计网格类型等信息； 网格重剖分模块：支持对已有网格进行重剖分； 网格文件导出模块：支持对已有网格进行不同格式的导出（inp stl obj vtk 等）； | J35: 支持在MxSim.GUI.3.0版本中具备以下网格功能模块: 网格自定义剖分模块：支持拾取线、面、体创建包围盒\球进行自定义区域加密；支持创建包围盒\球\圆柱进行自定义区域加密； 网格变换模块：支持对网格进行旋转、平移、镜像、阵列变换操作； 网格质量检测模块：支持1D 2D 3D 网格进行质量检测； 网格手动生成模块： 支持网格通过拉伸、扫掠等手动生成； 网格信息统计模块：支持统计网格类型等信息； 网格重剖分模块：支持对已有网格进行重剖分； 网格文件导出模块：支持对已有网格进行不同格式的导出（inp stl obj vtk 等）； （2）使用已有几何/网格文件测试算例，无需技术服务部及测试部额外制作算例。 | K35: 无 | L35: 否 | M35: 否 | N35: 是 | O35: 7级 | P35: 殷思麒 | Q35: P1 | R35: P1 | T35: =SUBSTITUTE(R35,"P","") -> 1 | V35: 2026 | W35: 46112 | X35: MxSim.Mechanical-通用-GUI-V3.0.0 | Z35: 44 | AE35: 46023 | AF35: 46112 | AP35: 8219 | AQ35: 19998 | AR35: =SUM(Y35:AD35) -> 44 | AS35: =AR35*8 -> 352
A36: 公司关联产品需求 | B36: 高 | C36: 是 | D36: 多物理场与智算平台-自研 | E36: MxSim.Motor | F36: Mesh | G36: 当前不支持齿槽转矩分析时，定子自动截断定子齿部分，对齿部分网格进行精细剖分，定子轭部网格粗剖分 | H36: 支持齿槽转矩分析时，定子自动截断定子齿部分，对齿部分网格进行精细剖分，定子轭部网格粗剖分功能 | I36: 具备齿槽转矩分析时，定子自动截断定子齿部分，对齿部分网格进行精细剖分，定子轭部网格粗剖分功能 | J36: 具备齿槽转矩分析时，定子自动截断定子齿部分，对齿部分网格进行精细剖分，定子轭部网格粗剖分功能。 1. 打开软件，进行齿槽转矩分析时，定子自动截断定子齿部分，对齿部分网格进行精细剖分，定子轭部网格粗剖分。 2. 使用已有几何/网格文件测试算例，无需技术服务部及测试部额外制作算例。 | K36: 无 | L36: 否 | M36: 否 | N36: 是 | O36: 7级 | P36: 殷思麒 | Q36: P1 | R36: P1 | T36: =SUBSTITUTE(R36,"P","") -> 1 | V36: 2026 | W36: 46112 | X36: MxSim.Motor电机综合智能仿真分析软件-GUI-V2.0.0 | Z36: 5 | AE36: 46023 | AF36: 46112 | AP36: 8263 | AQ36: 20045 | AR36: =SUM(Y36:AD36) -> 5 | AS36: =AR36*8 -> 40
A37: 公司关联产品需求 | B37: 高 | C37: 是 | D37: 通用结构平台-自研 | E37: MxSim.Mech | F37: Mesh | G37: 当前版本不支持复杂工程部件的STL网格一键生成 | H37: 支持复杂工程部件的STL模型三角形网格自动生成 | I37: 支持类似转向架、曲面铸件等复杂工程算例的STL模型三角形网格自动生成 | J37: 支持类似转向架、曲面铸件等复杂工程算例的STL模型表面三角网格自动生成。 验收过程： 1.打开软件，导入测试STL模型文件，输入剖分尺寸后点击剖分，可自动生成均匀三角网格。 2.使用已有几何文件测试算例，无需技术服务部及测试部额外制作算例。 | K37: 无 | L37: 否 | M37: 否 | N37: 否 | O37: 7级 | P37: 黄育民 | Q37: P0 | R37: P1 | T37: 1 | V37: 2026 | W37: 46112 | X37: MxSim.Mechanical-通用-GUI-V3.0.0 | Y37: 20 | AE37: 46023 | AF37: 46112 | AP37: 8220 | AQ37: 19999 | AR37: =SUM(Y37:AD37) -> 20 | AS37: =AR37*8 -> 160
A38: 市场需求 | B38: 高 | C38: 否 | D38: 云泊 | E38: 云泊商业项目 | F38: 云泊开发项目 | G38: 云泊界面开发 | H38: 云泊界面开发 | I38: 根据项目需求完成云泊项目开发工作 | J38: 无需算例，无需内部迭代测试 | K38: 无 | L38: 否 | M38: 否 | N38: 否 | O38: 7级 | P38: 黄育民 | Q38: P0 | R38: P1 | T38: 1 | V38: 2026 | W38: 46112 | X38: 通用CAE前后处理和网格剖分引擎二期攻关项目（商业项目）V1.0.4 | Y38: 30 | AE38: 46023 | AF38: 46112 | AP38: 8211 | AQ38: 20021 | AR38: =SUM(Y38:AD38) -> 30 | AS38: =AR38*8 -> 240
A39: 公司关联产品需求 | B39: 高 | C39: 是 | D39: 通用结构平台-自研 | E39: MxSim.Motor | F39: Mesh | G39: 界面优化电机版本不支持二维三角形一键网格剖分需求 | H39: 支持二维三角形一键网格剖分需求 | I39: 电机软件支持二维三角形一键网格剖分 | J39: 1、打开软件，支持网格生成前，各部件网格尺寸设置、部件边界网格尺寸设置以及曲线近似网格设置等操作， 所有网格设置完成后，点击生成，一键生成部件所有网格；气隙处要根据不同分析特殊处理外， 其他相邻部件间要保证共节点的需求 2.使用已有几何文件测试算例，无需技术服务部及测试部额外制作算例。 | K39: 无 | L39: 否 | M39: 否 | N39: 是 | O39: 7级 | P39: 黄育民 | Q39: P0 | R39: P1 | T39: 1 | V39: 2026 | W39: 46112 | X39: MxSim.Motor电机综合智能仿真分析软件-GUI-V2.0.0 | Y39: 2 | AE39: 46023 | AF39: 46112 | AP39: 8264 | AQ39: 20046 | AR39: =SUM(Y39:AD39) -> 2 | AS39: =AR39*8 -> 16
A40: 公司关联产品需求 | B40: 高 | C40: 是 | D40: 通用结构平台-自研 | E40: MxSim.Motor | F40: Mesh | G40: 当前版本不支持部件面网格尺寸大小设置 | H40: 支持部件面网格尺寸大小设置 | I40: 电机软件支持部件面网格尺寸大小设置 | J40: 1. 打开软件，界面支持部件面网格尺寸大小设置，通过拾取部件，对部件面网格进行大小设置，可以和体网格一起设置， 最后一键网格剖分生成所有； 2.使用已有几何文件测试算例，无需技术服务部及测试部额外制作算例。 | K40: 无 | L40: 否 | M40: 否 | N40: 是 | O40: 7级 | P40: 黄育民 | Q40: P0 | R40: P1 | T40: 1 | V40: 2026 | W40: 46112 | X40: MxSim.Motor电机综合智能仿真分析软件-GUI-V2.0.0 | Y40: 2 | AE40: 46023 | AF40: 46112 | AP40: 8266 | AQ40: 20048 | AR40: =SUM(Y40:AD40) -> 2 | AS40: =AR40*8 -> 16
A41: 公司关联产品需求 | B41: 高 | C41: 是 | D41: 通用结构平台-自研 | E41: MxSim.Mech | F41: Mesh | G41: 当前MxSim.GUI.2.0版本只支持部分网格功能模块 | H41: 网格变换模块、网格质量检测模块、 网格重剖分模块、网格文件导出模块。 | I41: 网格变换模块：支持对网格进行旋转、平移、镜像、阵列变换操作； 网格质量检测模块：支持1D 2D 3D 网格进行质量检测； 网格重剖分模块：支持对已有网格进行重剖分； 网格文件导出模块：支持对已有网格进行不同格式的导出（inp stl obj vtk 等）； | J41: 1.支持在MxSim.GUI.3.0版本中具备以下网格功能模块: 网格变换模块：支持对网格进行旋转、平移、镜像、阵列变换操作； 网格质量检测模块：支持1D 2D 3D 网格进行质量检测； 网格重剖分模块：支持对已有网格进行重剖分； 网格文件导出模块：支持对已有网格进行不同格式的导出（inp stl obj vtk 等）； 2.使用已有几何/网格文件测试算例，无需技术服务部及测试部额外制作算例。 | K41: 无 | L41: 否 | M41: 否 | N41: 是 | O41: 7级 | P41: 黄育民 | Q41: P0 | R41: P1 | T41: 1 | V41: 2026 | W41: 46112 | X41: MxSim.Mechanical-通用-GUI-V3.0.0 | Y41: 20 | AE41: 46023 | AF41: 46112 | AP41: 8221 | AQ41: 20000 | AR41: =SUM(Y41:AD41) -> 20 | AS41: =AR41*8 -> 160 | AT41: 2.27创建子任务，工时均归属黄育民
A42: 市场需求 | B42: 高 | C42: 是 | D42: 多物理场与智算平台-航天一院 | E42: MxSim.CFD | F42: Mesh | G42: 当前版本不支持Mx.CFD要求的流体域的结构化六面体边界层网格 | H42: 支持流体域的结构化六面体边界层 | I42: 为分块六面体模型的各向异性纯六面体共节点网格生成提供技术支持 | J42: 无需算例，无需内部迭代测试 | K42: 无 | L42: 否 | M42: 否 | N42: 否 | O42: 7级 | P42: 李政斌 | Q42: P2 | R42: P2 | T42: 2 | V42: 2026 | W42: 46112 | X42: MxSim.CFD可压流体软件开发项目-GUI-V2.0.0 | AA42: 7 | AE42: 46023 | AF42: 46112 | AP42: 8271 | AQ42: 19951 | AR42: =SUM(Y42:AD42) -> 7 | AS42: =AR42*8 -> 56
A43: 公司关联产品需求 | B43: 高 | C43: 是 | D43: 多物理场与智算平台-自研 | E43: MxSim.CFD | F43: Mesh | G43: 当前版本在凹角处容易提前发生碰撞，自适应控制推进方向与距离的算法不完善。 | H43: 支持基于椭圆偏微分方程的全局边界层网格生成方法。 | I43: 支持基于椭圆偏微分方程的边界层网格生成算法，可以生成全局的边界层网格 | J43: 对于多数无复杂几何特征，无奇异拓扑结构的全模型，软件可以生成全局边界层网格。 1. 导入全模型的几何模型，设定壁面与非壁面，设定初始层厚与层厚增长率以及最大层数，生成全局边界层网格。 2. 使用已有几何文件测试算例，无需技术服务部及测试部额外制作算例。 | K43: 无 | L43: 否 | M43: 否 | N43: 否 | O43: 7级 | P43: 李政斌 | Q43: P2 | R43: P2 | T43: 2 | V43: 2026 | W43: 46112 | X43: MxSim.CFD可压流体软件开发项目-GUI-V2.0.0 | AA43: 30 | AE43: 46023 | AF43: 46112 | AP43: 8272 | AQ43: 19952 | AR43: =SUM(Y43:AD43) -> 30 | AS43: =AR43*8 -> 240
A44: 公司关联产品需求 | B44: 高 | C44: 是 | D44: 多物理场与智算平台-自研 | E44: MxSim.CFD | F44: Mesh | G44: 当前版本的边界层生成算法为独立算法库，与几何网格渲染的耦合性不足，需要提升交互效率。 | H44: 提供基于MxMesh的边界层生成标准接口 | I44: 支持在MxMesh中可以通过标准接口调用边界层生成算法 | J44: 支持在Mx.Mech软件或其余软件中使用GUI界面调用边界层网格生成功能 。 1. 导入全模型/半模型/管道模型的几何模型，设定壁面与非壁面，设定初始层厚与层厚增长率以及最大层数，生成边界层网格。 2. 使用已有几何文件测试算例，无需技术服务部及测试部额外制作算例。 | K44: 无 | L44: 否 | M44: 否 | N44: 否 | O44: 7级 | P44: 李政斌 | Q44: P2 | R44: P1 | T44: 1 | V44: 2026 | W44: 46112 | X44: MxSim.CFD可压流体软件开发项目-GUI-V2.0.0 | AA44: 7 | AE44: 46023 | AF44: 46112 | AP44: 8273 | AQ44: 19953 | AR44: =SUM(Y44:AD44) -> 7 | AS44: =AR44*8 -> 56
A45: 公司关联产品需求 | B45: 高 | C45: 是 | D45: 多物理场与智算平台-自研 | E45: MxSim.Motor | F45: Mesh | G45: 当前版本不支持Mx.motor要求的电机圆柱气隙专用网格 | H45: 支持电机圆柱气隙专用的band网格 | I45: 支持生成电机的气隙部分网格，可以生成电机气隙部分所需的band网格。 | J45: 支持在Mx.Motor中生成电机圆柱气隙所需的band网格 。 1.打开软件，用户可以独立设定气隙部分网格，通过设置其映射角度，其映射角度设置存在一定范围，比如0.05-3deg左右，设置完成后，通过一键生成网格。 2. 使用已有几何文件测试算例，无需技术服务部及测试部额外制作算例。 | K45: 无 | L45: 否 | M45: 否 | N45: 否 | O45: 7级 | P45: 李政斌 | Q45: P2 | R45: P2 | T45: 2 | V45: 2026 | W45: 46112 | X45: MxSim.Motor电机综合智能仿真分析软件-GUI-V2.0.0 | AA45: 15 | AE45: 46023 | AF45: 46112 | AP45: 8267 | AQ45: 20049 | AR45: =SUM(Y45:AD45) -> 15 | AS45: =AR45*8 -> 120
A46: 公司关联产品需求 | B46: 高 | C46: 是 | D46: 多物理场与智算平台-自研 | E46: MxSim.CFD | F46: Mesh | G46: 当前版本不支持边界层网格正交性优化 | H46: 优化边界层网格质量 | I46: 提升边界层网格的正交性 | J46: 提升边界层网格的正交性 。 1. 输入完整无自交的边界层网格，选择边界层网格质量优化，设定迭代次数与收敛容差，迭代提升边界层网格的正交性。 2. 使用已有几何文件测试算例，无需技术服务部及测试部额外制作算例。 | K46: 无 | L46: 否 | M46: 否 | N46: 否 | O46: 7级 | P46: 李政斌 | Q46: P2 | R46: P2 | T46: 2 | V46: 2026 | W46: 46112 | X46: MxSim.CFD可压流体软件开发项目-GUI-V2.0.0 | AA46: 7 | AE46: 46023 | AF46: 46112 | AP46: 8274 | AQ46: 19954 | AR46: =SUM(Y46:AD46) -> 7 | AS46: =AR46*8 -> 56
A47: 公司关联产品需求 | B47: 中 | C47: 是 | D47: 通用结构平台-自研 | E47: MxSim.Mech | F47: CG | H47: 界面重构渲染层迁移 | I47: 1. 将渲染层迁出交互相关功能为交互层，并针对前处理、后处理提供额外的前处理/后处理交互层，降低渲染层耦合性 2. 优化界面功能在交互层的对应关系，抽象统一的tool基类，提高拓展性，加快后续草图等交互功能开发效率 | J47: 验收标准：无需算例， 1. 保证迁移后渲染相关功能能够正常使用 | K47: 无 | L47: 否 | M47: 否 | N47: 是 | O47: 7级 | P47: 林家正 | Q47: p1 | R47: p2 | S47: 2 | T47: 2 | U47: 1 | V47: 2026 | W47: 46112 | X47: MxSim.Mechanical-通用-GUI-V3.0.0 | Z47: 36 | AE47: 46023 | AF47: 46112 | AP47: 8223 | AQ47: 20004 | AR47: =SUM(Y47:AD47) -> 36 | AS47: =AR47*8 -> 288
A48: 公司关联产品需求 | B48: 中 | C48: 是 | D48: 通用结构平台-自研 | E48: MxSim.Mech | F48: CG | H48: 草图功能开发 | I48: 1. 为草图创建提供基础吸附功能，可吸附对其参考网格、已存在几何 | J48: 验收标准：无需算例，可以直接在软件中进行创建，效果与spaceclaim类似 1. 保证吸附的可视化效果与实际位置一致 2. 能够正确与创建功能联动 | K48: SpaceClaim | L48: 否 | M48: 否 | N48: 是 | O48: 7级 | P48: 林家正 | Q48: p1 | R48: p2 | S48: 2 | T48: 2 | U48: 1 | V48: 2026 | W48: 46112 | X48: MxSim.Mechanical-通用-GUI-V3.0.0 | Z48: 12 | AE48: 46023 | AF48: 46112 | AP48: 8224 | AQ48: 20005 | AR48: =SUM(Y48:AD48) -> 12 | AS48: =AR48*8 -> 96
A49: 产品主动规划需求 | B49: 中 | C49: 是 | D49: 多物理场与智算平台-自研 | E49: MxSim.Motor | F49: CG | H49: motor渲染版本迁移 | I49: 1. 将渲染从rebuild版本迁移到界面重构版本 2. 保证前处理、后处理功能在移植后正常 3. 保证电机开发的新功能在迁移后正常 | J49: 验收标准：无需算例 1. 保证原有渲染功能与相对于界面重构版本的新功能在迁移后正常运行 | K49: Motor | L49: 否 | M49: 否 | N49: 是 | O49: 7级 | P49: 林家正 | R49: p2 | V49: 2026 | W49: 46112 | X49: MxSim.Motor电机综合智能仿真分析软件-GUI-V2.0.0 | Z49: 20 | AE49: 46023 | AF49: 46112 | AP49: 8268 | AQ49: 20050 | AR49: =SUM(Y49:AD49) -> 20 | AS49: =AR49*8 -> 160
A50: 公司关联产品需求 | B50: 高 | C50: 是 | D50: 疲劳产品平台-自研 | E50: MxSim.Fatigue | F50: CG | H50: 华为云渲染引擎接入 | I50: 1. 配合对疲劳所需渲染功能使用华为云渲染引擎接入替代 | J50: 验收标准：无需算例 1. 使用华为云渲染引擎替代疲劳的渲染功能，保证原有渲染功能在使用华为云渲染引擎的前提下正常运行 | K50: 无 | L50: 否 | M50: 否 | N50: 是 | O50: 7级 | P50: 潜森伟 | Q50: P1 | R50: p2 | S50: 2 | T50: 2 | U50: 1 | V50: 2026 | W50: 46112 | X50: MxSim.Fatigue疲劳软件-通用-GUI-V3.0.0 | Z50: 68 | AE50: 46023 | AF50: 46112 | AP50: 8181 | AQ50: 19962 | AR50: =SUM(Y50:AD50) -> 68 | AS50: =AR50*8 -> 544
A51: 公司关联产品需求 | B51: 中 | C51: 是 | D51: 通用结构平台-自研 | E51: MxSim.Mech | F51: CG | H51: 草图 | I51: 1. 提供对二维几何创建的功能：线、圆、矩形、切线、样条曲线、椭圆、圆弧 2. 可以通过拾取选择草图平面，并且带有预览功能 | J51: 验收标准：无需算例，可以直接在软件中进行创建，效果与spaceclaim类似 1. 可以正确创建对应二维几何 2. 能够正确确定草图平面 | K51: SpaceClaim | L51: 否 | M51: 否 | N51: 是 | O51: 7级 | P51: 张国海 | Q51: P2 | R51: p2 | V51: 2026 | W51: 46112 | X51: MxSim.Mechanical-通用-GUI-V3.0.0 | AA51: 20 | AE51: 46023 | AF51: 46112 | AP51: 8222 | AQ51: 20001 | AR51: =SUM(Y51:AD51) -> 20 | AS51: =AR51*8 -> 160
A52: 公司关联产品需求 | B52: 中 | C52: 是 | D52: 通用结构平台-自研 | E52: MxSim.Mech | F52: CG | H52: 草图 | I52: 1. 对创建中的尺寸给出标识效果，且随尺寸变化自适应大小与位置 2. 对于创建中的相关参数给出可编辑标签，编辑会与鼠标位置、尺寸标识正常联动 | J52: 验收标准：无需算例，可以直接在软件中进行，效果与spaceclaim类似 1. 标识能够正常随创建时的鼠标移动正常自适应 2. 标识的参数块可编辑，并且编辑确认后可以正确修改联动鼠标位置与尺寸 | K52: SpaceClaim | L52: 否 | M52: 否 | N52: 是 | O52: 7级 | P52: 张国海 | Q52: P2 | R52: p2 | V52: 2026 | W52: 46112 | X52: MxSim.Mechanical-通用-GUI-V3.0.0 | AA52: 18 | AE52: 46023 | AF52: 46112 | AP52: 8222 | AQ52: 20002 | AR52: =SUM(Y52:AD52) -> 18 | AS52: =AR52*8 -> 144
A53: 公司关联产品需求 | B53: 中 | C53: 是 | D53: 通用结构平台-自研 | E53: MxSim.Mech | F53: CG | H53: 网格编辑 | I53: 1. 对于网格提供单一网格节点在某一参考平面上的的可交互式移动功能 | J53: 验收标准：无需算例，可以直接在软件中进行创建 1. 能够正确修改网格中的单一节点 | K53: SpaceClaim | L53: 否 | M53: 否 | N53: 是 | O53: 7级 | P53: 张国海 | Q53: P2 | V53: 2026 | W53: 46112 | X53: MxSim.Mechanical-通用-GUI-V3.0.0 | AA53: 10 | AE53: 46023 | AF53: 46112 | AP53: 8225 | AQ53: 20006 | AR53: =SUM(Y53:AD53) -> 10 | AS53: =AR53*8 -> 80
A54: 市场需求 | B54: 高 | C54: 是 | D54: 多物理场与智算平台-航天一院 | E54: MxSim.CFD | F54: CG | H54: 流体注释功能 | I54: 具备流体注释功能以及注释相关的鼠标交互功能 | J54: 添加注释，包括文字、二维线、三维箭头以及导入log等，所有注释均可通过鼠标拖动至所需位置。 | K54: 无 | L54: 否 | M54: 否 | N54: 否 | O54: 7级 | P54: 张国海 | Q54: P2 | R54: P2 | V54: 2026 | W54: 46112 | X54: MxSim.CFD可压流体软件开发项目-GUI-V2.0.0 | AA54: 20 | AE54: 46023 | AF54: 46112 | AP54: 9203 | AQ54: 21597 | AT54: 3.17新增此任务
A55: 公司关联产品需求 | B55: 高 | C55: 是 | D55: 通用结构平台-自研 | E55: MxSim.Mech | F55: CG | H55: 草图 | I55: 1. 对于倒角、拉伸、平移、旋转功能提供可交互式编辑功能 | J55: 验收标准：无需算例，可以直接在软件中进行创建 1. 正确拾取目标几何线、体，显示对应控件 2. 正确通过移动控件，实时生成对应效果 | K55: SpaceClaim | L55: 否 | M55: 否 | N55: 否 | O55: 7级 | P55: 张国海 | Q55: P2 | V55: 2026 | W55: 46112 | X55: MxSim.Mechanical-通用-GUI-V3.0.0 | AA55: 0 | AE55: 46023 | AF55: 46112 | AP55: 8222 | AQ55: 20003 | AR55: =SUM(Y55:AD55) -> 0 | AS55: =AR55*8 -> 0 | AT55: 3.17删除此任务，原工时为20人天
A56: 公司关联产品需求 | B56: 中 | C56: 是 | D56: 通用结构平台-自研 | E56: MxSim.Mech | F56: CG | H56: 渲染相关的管理工作 | I56: 渲染相关的管理工作 | J56: 无需验收 | K56: 无 | L56: 否 | M56: 否 | N56: 否 | O56: 7级 | P56: 彭武绍 | Q56: P2 | V56: 2026 | W56: 46112 | X56: MxSim.Mechanical-通用-GUI-V3.0.0 | AA56: 6 | AE56: 46023 | AF56: 46112 | AP56: 8226 | AQ56: 20007 | AR56: =SUM(Y56:AD56) -> 6 | AS56: =AR56*8 -> 48
A57: 公司关联产品需求 | B57: 高 | C57: 是 | D57: 显式动力学平台-自研 | E57: MxSim.Dyna | F57: GUI | H57: mpi类型限制或提示 | I57: 使用mpi版本是需要用bat脚本提交，不是exe，建议界面能够提示一下，或者限制一下 | J57: 验收过程： 1.打开软件，进行软件操作，满足*关键规格与描述，满足需求文档中或项目的具体需求。 测试部门：产品测试部 | K57: MXDynaBatchRUN | M57: 否 | N57: 是 | P57: 向强 | Q57: P2 | R57: P2 | V57: 2026 | W57: 46112 | X57: MxSim.Dyna-通用-GUI-V3.0.4 | AA57: 0.5 | AE57: 46023 | AF57: 46112 | AP57: 8174 | AQ57: 19955 | AR57: =SUM(Y57:AD57) -> 0.5 | AS57: =AR57*8 -> 4
A58: 公司关联产品需求 | B58: 高 | C58: 是 | D58: 显式动力学平台-自研 | E58: MxSim.Dyna | F58: GUI | H58: 重复算例重编号（显隐） | I58: 选择的算例文件夹下有k和mx在一起时会计算两次 当遍历一个文件夹，里面同时存在k mx或者abaqus mx的时候，只提取商软文件作为批量计算的文件。只有当文件夹里面不存在商软文件时，才回将mx文件作为批量计算目标，可以在抓取计算文件的时候，给文件名加上一个序号 | J58: 验收过程： 1.打开软件，进行软件操作，满足*关键规格与描述，满足需求文档中或项目的具体需求。 测试部门：产品测试部 | K58: MXDynaBatchRUN/ MXMechBatchRUN | M58: 否 | N58: 是 | P58: 向强 | Q58: P2 | R58: P2 | V58: 2026 | W58: 46112 | X58: MxSim.Dyna-通用-GUI-V3.0.4 | AA58: 3 | AE58: 46023 | AF58: 46112 | AP58: 8175 | AQ58: 19956 | AR58: =SUM(Y58:AD58) -> 3 | AS58: =AR58*8 -> 24
A59: 公司关联产品需求 | B59: 高 | C59: 是 | D59: 显式动力学平台-自研 | E59: MxSim.Dyna | F59: GUI | H59: 终止当前算例（显隐） | I59: 批处理提交之后，希望实现单独中止一个算例的计算，进入下一个算例计算，允许手动选择，类似求解器提交按 ctrl+c 会跳过当前这个（mx 和 lsdyna 和 abaqus 都要做） | J59: 验收过程： 1.打开软件，进行软件操作，满足*关键规格与描述，满足需求文档中或项目的具体需求。 测试部门：产品测试部 | K59: MXDynaBatchRUN/ MXMechBatchRUN | M59: 否 | N59: 是 | P59: 向强 | Q59: P2 | R59: P2 | V59: 2026 | W59: 46112 | X59: MxSim.Dyna-通用-GUI-V3.0.4 | AA59: 2 | AE59: 46023 | AF59: 46112 | AP59: 8176 | AQ59: 19957 | AR59: =SUM(Y59:AD59) -> 2 | AS59: =AR59*8 -> 16
A60: 公司关联产品需求 | B60: 高 | C60: 是 | D60: 显式动力学平台-自研 | E60: MxSim.Dyna | F60: GUI | H60: 自定义命令（显隐） | I60: 可以自主添加命令以及后缀，后缀如-f，-fdump等 | J60: 验收过程： 1.打开软件，进行软件操作，满足*关键规格与描述，满足需求文档中或项目的具体需求。 测试部门：产品测试部 | K60: MXDynaBatchRUN/ MXMechBatchRUN | M60: 否 | N60: 是 | P60: 向强 | Q60: P2 | R60: P2 | V60: 2026 | W60: 46112 | X60: MxSim.Dyna-通用-GUI-V3.0.4 | AA60: 2 | AE60: 46023 | AF60: 46112 | AP60: 8177 | AQ60: 19958 | AR60: =SUM(Y60:AD60) -> 2 | AS60: =AR60*8 -> 16
A61: 公司关联产品需求 | B61: 高 | C61: 是 | D61: 显式动力学平台-自研 | E61: MxSim.Dyna | F61: GUI | H61: abaqus inp文件计算结果对比 | I61: 新增abaqus inp文件计算结果对比功能 | J61: 验收过程： 1.打开软件，进行软件操作，满足*关键规格与描述，满足需求文档中或项目的具体需求。 测试部门：产品测试部 | K61: MXDynaBatchRUN | M61: 否 | N61: 是 | P61: 向强 | Q61: P2 | R61: P2 | V61: 2026 | W61: 46112 | X61: MxSim.Dyna-通用-GUI-V3.0.4 | AA61: 1 | AE61: 46023 | AF61: 46112 | AP61: 8178 | AQ61: 19959 | AR61: =SUM(Y61:AD61) -> 1 | AS61: =AR61*8 -> 8
A62: 公司关联产品需求 | B62: 高 | C62: 是 | D62: 显式动力学平台-自研 | E62: MxSim.Dyna | F62: GUI | H62: 批处理工具关键字对齐（显隐） | I62: 批处理工具求解器与界面关键字对齐 | J62: 验收过程： 1.打开软件，进行软件操作，满足*关键规格与描述，满足需求文档中或项目的具体需求。 测试部门：产品测试部 | K62: MXDynaBatchRUN/ MXMechBatchRUN | M62: 否 | N62: 是 | P62: 向强 | Q62: P2 | R62: P2 | V62: 2026 | W62: 46112 | X62: MxSim.Dyna-通用-GUI-V3.0.4 | AA62: 10 | AE62: 46023 | AF62: 46112 | AP62: 8179 | AQ62: 19960 | AR62: =SUM(Y62:AD62) -> 10 | AS62: =AR62*8 -> 80
A63: 公司关联产品需求 | B63: 高 | C63: 是 | D63: 显式动力学平台-自研 | E63: MxSim.Dyna | F63: GUI | H63: dyna界面重构 | I63: dyna界面重构 | J63: 验收过程： 1.打开软件，进行软件操作，满足*关键规格与描述，满足需求文档中或项目的具体需求。 测试部门：产品测试部 | K63: MxDyna V3.0 | M63: 否 | N63: 否 | P63: 向强 | Q63: P2 | R63: P2 | V63: 2026 | W63: 46112 | X63: MxSim.Dyna-通用-GUI-V3.0.4 | AA63: 47.5 | AE63: 46023 | AF63: 46112 | AP63: 8180 | AQ63: 19961 | AR63: =SUM(Y63:AD63) -> 47.5 | AS63: =AR63*8 -> 380
A64: 公司关联产品需求 | B64: 高 | C64: 是 | D64: 多物理场与智算平台-自研 | E64: MxSim.AI | F64: GUI | G64: AI模型树 | H64: AI模型树 | I64: 按照项目要求完成开发 | J64: 1、打开软件，进行操作，满足具体需求 | K64: 无 | L64: 否 | M64: 否 | N64: 是 | O64: 5级 | P64: 肖志钢 | Q64: P1 | R64: P2 | S64: 1 | T64: 2 | U64: 2 | V64: 2026 | W64: 46112 | X64: MxSim.AI-通用-GUI-V1.0.0 | Z64: 15 | AE64: 46023 | AF64: 46112 | AP64: 8275 | AQ64: 19938 | AR64: =SUM(Y64:AD64) -> 15 | AS64: =AR64*8 -> 120
A65: 公司关联产品需求 | B65: 高 | C65: 是 | D65: 多物理场与智算平台-自研 | E65: MxSim.AI | F65: GUI | G65: 仿真模型树 | H65: 仿真模型树 | I65: 按照项目要求完成开发 | J65: 1、打开软件，进行操作，满足具体需求 | K65: 无 | L65: 否 | M65: 否 | N65: 是 | O65: 5级 | P65: 肖志钢 | Q65: P1 | R65: P2 | S65: 1 | T65: 2 | U65: 2 | V65: 2026 | W65: 46112 | X65: MxSim.AI-通用-GUI-V1.0.0 | Z65: 15 | AE65: 46023 | AF65: 46112 | AP65: 8276 | AQ65: 19939 | AR65: =SUM(Y65:AD65) -> 15 | AS65: =AR65*8 -> 120
A66: 公司关联产品需求 | B66: 高 | C66: 是 | D66: 多物理场与智算平台-自研 | E66: MxSim.AI | F66: GUI | G66: 渲染窗口 | H66: 渲染窗口 | I66: 按照项目要求完成开发 | J66: 1、打开软件，进行操作，满足具体需求 | K66: 无 | L66: 否 | M66: 否 | N66: 是 | O66: 5级 | P66: 李靓杰 | Q66: P2 | R66: P2 | S66: 1 | T66: 2 | U66: 2 | V66: 2026 | W66: 46112 | X66: MxSim.AI-通用-GUI-V1.0.0 | AA66: 18 | AE66: 46023 | AF66: 46112 | AP66: 8277 | AQ66: 19940 | AR66: =SUM(Y66:AD66) -> 18 | AS66: =AR66*8 -> 144
A67: 公司关联产品需求 | B67: 高 | C67: 是 | D67: 多物理场与智算平台-自研 | E67: MxSim.AI | F67: GUI | G67: 新建数据集 | H67: 新建数据集 | I67: 开发新建仿真数据集、新建训练数据集界面及功能。 | J67: 1、打开软件，进行操作，满足具体需求 | K67: 无 | L67: 否 | M67: 否 | N67: 是 | O67: 5级 | P67: 吴维煜 | Q67: P2 | R67: P2 | S67: 1 | T67: 2 | U67: 2 | V67: 2026 | W67: 46112 | X67: MxSim.AI-通用-GUI-V1.0.0 | AA67: 15 | AE67: 46023 | AF67: 46112 | AP67: 8278 | AQ67: 19941 | AR67: =SUM(Y67:AD67) -> 15 | AS67: =AR67*8 -> 120 | AT67: 3.10变更基线，人天从10变成15
A68: 公司关联产品需求 | B68: 高 | C68: 是 | D68: 多物理场与智算平台-自研 | E68: MxSim.AI | F68: GUI | G68: 文件管理 | H68: 文件管理 | I68: 项目过程中生成的文件的落盘和起盘 | J68: 1、打开软件，进行操作，满足具体需求 | K68: 无 | L68: 否 | M68: 否 | N68: 是 | O68: 5级 | P68: 肖志钢 | Q68: P1 | R68: P2 | S68: 1 | T68: 2 | U68: 2 | V68: 2026 | W68: 46112 | X68: MxSim.AI-通用-GUI-V1.0.0 | Z68: 16 | AE68: 46023 | AF68: 46112 | AP68: 8279 | AQ68: 19942 | AR68: =SUM(Y68:AD68) -> 16 | AS68: =AR68*8 -> 128
A69: 公司关联产品需求 | B69: 高 | C69: 是 | D69: 多物理场与智算平台-自研 | E69: MxSim.AI | F69: GUI | G69: 撤销/重做 | H69: 撤销/重做 | I69: 开发软件操作过程中对功能步骤进行撤销和重做的功能。 | J69: 1、打开软件，进行操作，满足具体需求 | K69: 无 | L69: 否 | M69: 否 | N69: 是 | O69: 5级 | P69: 肖志钢 | Q69: P1 | R69: P2 | S69: 1 | T69: 2 | U69: 2 | V69: 2026 | W69: 46112 | X69: MxSim.AI-通用-GUI-V1.0.0 | Z69: 20 | AE69: 46023 | AF69: 46112 | AP69: 8280 | AQ69: 19943 | AR69: =SUM(Y69:AD69) -> 20 | AS69: =AR69*8 -> 160
A70: 公司关联产品需求 | B70: 高 | C70: 是 | D70: 多物理场与智算平台-自研 | E70: MxSim.AI | F70: GUI | G70: 数据中台 | H70: 数据中台 | I70: 按照项目要求完成开发 | J70: 1、打开软件，进行操作，满足具体需求 | K70: 无 | L70: 否 | M70: 否 | N70: 是 | O70: 5级 | P70: 李靓杰 | Q70: P2 | R70: P2 | S70: 1 | T70: 2 | U70: 2 | V70: 2026 | W70: 46112 | X70: MxSim.AI-通用-GUI-V1.0.0 | AA70: 18 | AE70: 46023 | AF70: 46112 | AP70: 8281 | AQ70: 19944 | AR70: =SUM(Y70:AD70) -> 18 | AS70: =AR70*8 -> 144
A71: 公司关联产品需求 | B71: 高 | C71: 是 | D71: 多物理场与智算平台-自研 | E71: MxSim.AI | F71: GUI | G71: 智能计算 | H71: 智能计算 | I71: 按照项目要求完成开发 | J71: 1、打开软件，进行操作，满足具体需求 | K71: 无 | L71: 否 | M71: 否 | N71: 是 | O71: 5级 | P71: 吴维煜 | Q71: P2 | R71: P2 | S71: 1 | T71: 2 | U71: 2 | V71: 2026 | W71: 46112 | X71: MxSim.AI-通用-GUI-V1.0.0 | AA71: 11 | AE71: 46023 | AF71: 46112 | AP71: 8282 | AQ71: 19945 | AR71: =SUM(Y71:AD71) -> 11 | AS71: =AR71*8 -> 88 | AT71: 3.10变更基线，人天从8变成11
A72: 公司关联产品需求 | B72: 高 | C72: 是 | D72: 多物理场与智算平台-自研 | E72: MxSim.AI | F72: GUI | G72: 智能训练与评估 | H72: 智能训练与评估界面 | I72: 按照项目要求完成开发 | J72: 1、打开软件，进行操作，满足具体需求 | K72: 无 | L72: 否 | M72: 否 | N72: 是 | O72: 5级 | P72: 李靓杰 | Q72: P2 | R72: P2 | S72: 1 | T72: 2 | U72: 2 | V72: 2026 | W72: 46112 | X72: MxSim.AI-通用-GUI-V1.0.0 | AA72: 15 | AE72: 46023 | AF72: 46112 | AP72: 8283 | AQ72: 19946 | AR72: =SUM(Y72:AD72) -> 15 | AS72: =AR72*8 -> 120
A73: 公司关联产品需求 | B73: 高 | C73: 是 | D73: 多物理场与智算平台-自研 | E73: MxSim.AI | F73: GUI | G73: 智能训练与评估 | H73: 智能训练与评估功能 | I73: 按照项目要求完成开发 | J73: 1、打开软件，进行操作，满足具体需求 | K73: 无 | L73: 否 | M73: 否 | N73: 是 | O73: 5级 | P73: 吴维煜 | Q73: P2 | R73: P2 | S73: 1 | T73: 2 | U73: 2 | V73: 2026 | W73: 46112 | X73: MxSim.AI-通用-GUI-V1.0.0 | AA73: 15 | AE73: 46023 | AF73: 46112 | AP73: 8284 | AQ73: 19947 | AR73: =SUM(Y73:AD73) -> 15 | AS73: =AR73*8 -> 120 | AT73: 3.10变更基线，人天从10变成15
A74: 公司关联产品需求 | B74: 高 | C74: 是 | D74: 多物理场与智算平台-自研 | E74: MxSim.AI | F74: GUI | G74: 界面美化 | H74: 界面美化 | I74: 界面美化 | J74: 1、打开软件，进行操作，满足具体需求 | K74: 无 | L74: 否 | M74: 否 | N74: 是 | O74: 5级 | P74: 李靓杰 | Q74: P2 | R74: P2 | S74: 1 | T74: 2 | U74: 2 | V74: 2026 | W74: 46112 | X74: MxSim.AI-通用-GUI-V1.0.0 | AA74: 15 | AE74: 46023 | AF74: 46112 | AP74: 8285 | AQ74: 19948 | AR74: =SUM(Y74:AD74) -> 15 | AS74: =AR74*8 -> 120
A75: 公司关联产品需求 | B75: 高 | C75: 是 | D75: 多物理场与智算平台-自研 | E75: MxSim.AI | F75: GUI | G75: 操作逻辑优化 | H75: 操作逻辑优化 | I75: 操作逻辑优化 | J75: 1、打开软件，进行操作，满足具体需求 | K75: 无 | L75: 否 | M75: 否 | N75: 是 | O75: 5级 | P75: 吴维煜 | Q75: P2 | R75: P2 | S75: 1 | T75: 2 | U75: 2 | V75: 2026 | W75: 46112 | X75: MxSim.AI-通用-GUI-V1.0.0 | AA75: 5 | AE75: 46023 | AF75: 46112 | AP75: 8286 | AQ75: 19949 | AR75: =SUM(Y75:AD75) -> 5 | AS75: =AR75*8 -> 40
A76: 公司关联产品需求 | B76: 高 | C76: 是 | D76: 通用结构平台-自研 | E76: MxSim.Fatigue | F76: GUI | H76: 热点损伤区域检测 | I76: 接入热点损伤区域检测算法代码 | J76: 验收过程： 1.打开软件，进行软件操作，满足*关键规格与描述，满足需求文档中或项目的具体需求。 验证算例例子： 1.使用求解器测试算例，无需技术服务部及测试部额外制作算例。 测试部门：产品测试部 | K76: nCode | L76: 否 | M76: 否 | N76: 是 | O76: 7级 | P76: 张开元 | Q76: P1 | R76: P1 | S76: =SUBSTITUTE(Q76,"P","") -> 1 | T76: =SUBSTITUTE(R76,"P","") -> 1 | U76: =SUBSTITUTE(S76,"P","") -> 1 | V76: 2026 | W76: 45747 | X76: MxSim.Fatigue疲劳软件-通用-GUI-V3.0.0 | Z76: 2 | AE76: 46023 | AF76: 46112 | AP76: 8182 | AQ76: 19963 | AR76: =SUM(Y76:AD76) -> 2 | AS76: =AR76*8 -> 16
A77: 公司关联产品需求 | B77: 高 | C77: 是 | D77: 通用结构平台-自研 | E77: MxSim.Fatigue | F77: GUI | H77: 材料参数自动修正功能（国重项目需求） | I77: 修改参数拟合界面，新增界面参数 | J77: 验收过程： 1.打开软件，进行软件操作，满足*关键规格与描述，满足需求文档中或项目的具体需求。 验证算例例子： 2.使用求解器测试算例，无需技术服务部及测试部额外制作算例。 测试部门：产品测试部 | K77: nCode | L77: 否 | M77: 否 | N77: 是 | O77: 7级 | P77: 张开元 | Q77: P1 | R77: P1 | S77: =SUBSTITUTE(Q77,"P","") -> 1 | T77: =SUBSTITUTE(R77,"P","") -> 1 | U77: =SUBSTITUTE(S77,"P","") -> 1 | V77: 2026 | W77: 45747 | X77: MxSim.Fatigue疲劳软件-通用-GUI-V3.0.0 | Z77: 3 | AE77: 46023 | AF77: 46112 | AP77: 8183 | AQ77: 19964 | AR77: =SUM(Y77:AD77) -> 3 | AS77: =AR77*8 -> 24
A78: 公司关联产品需求 | B78: 高 | C78: 是 | D78: 通用结构平台-自研 | E78: MxSim.Fatigue | F78: GUI | H78: 界面适配mxdb格式 | I78: 界面适配mxdb格式文件加载，包括生成xml，读取工况，后处理云图（014项目需求） | J78: 验收过程： 1.打开软件，进行软件操作，满足*关键规格与描述，满足需求文档中或项目的具体需求。 验证算例例子： 4.使用求解器测试算例，无需技术服务部及测试部额外制作算例。 测试部门：产品测试部 | K78: nCode | L78: 否 | M78: 否 | N78: 是 | O78: 7级 | P78: 张开元 | Q78: P1 | R78: P1 | S78: =SUBSTITUTE(Q78,"P","") -> 1 | T78: =SUBSTITUTE(R78,"P","") -> 1 | U78: =SUBSTITUTE(S78,"P","") -> 1 | V78: 2026 | W78: 45747 | X78: MxSim.Fatigue疲劳软件-通用-GUI-V3.0.0 | Z78: 5 | AE78: 46023 | AF78: 46112 | AP78: 8185 | AQ78: 19966 | AR78: =SUM(Y78:AD78) -> 5 | AS78: =AR78*8 -> 40
A79: 公司关联产品需求 | B79: 高 | C79: 是 | D79: 通用结构平台-自研 | E79: MxSim.Fatigue | F79: GUI | H79: 路谱载荷损伤占比 | I79: 新增一个显示路谱载荷损伤占比节点显示路谱损伤占比 | J79: 验收过程： 1.打开软件，进行软件操作，满足*关键规格与描述，满足需求文档中或项目的具体需求。 验证算例例子： 5.使用求解器测试算例，无需技术服务部及测试部额外制作算例。 测试部门：产品测试部 | K79: nCode | L79: 否 | M79: 否 | N79: 是 | O79: 7级 | P79: 张开元 | Q79: P1 | R79: P1 | S79: =SUBSTITUTE(Q79,"P","") -> 1 | T79: =SUBSTITUTE(R79,"P","") -> 1 | U79: =SUBSTITUTE(S79,"P","") -> 1 | V79: 2026 | W79: 45747 | X79: MxSim.Fatigue疲劳软件-通用-GUI-V3.0.0 | Z79: 3 | AE79: 46023 | AF79: 46112 | AP79: 8186 | AQ79: 19967 | AR79: =SUM(Y79:AD79) -> 3 | AS79: =AR79*8 -> 24
A80: 公司关联产品需求 | B80: 高 | C80: 是 | D80: 通用结构平台-自研 | E80: MxSim.Fatigue | F80: GUI | H80: 铆接界面 | I80: 开发铆接分析节点和铆接分析材料节点 | J80: 验收过程： 1.打开软件，进行软件操作，满足*关键规格与描述，满足需求文档中或项目的具体需求。 验证算例例子： 7.使用求解器测试算例，无需技术服务部及测试部额外制作算例。 测试部门：产品测试部 | K80: nCode | L80: 否 | M80: 否 | N80: 是 | O80: 7级 | P80: 张开元 | Q80: P1 | R80: P1 | S80: =SUBSTITUTE(Q80,"P","") -> 1 | T80: =SUBSTITUTE(R80,"P","") -> 1 | U80: =SUBSTITUTE(S80,"P","") -> 1 | V80: 2026 | W80: 45747 | X80: MxSim.Fatigue疲劳软件-通用-GUI-V3.0.0 | Z80: 4 | AE80: 46023 | AF80: 46112 | AP80: 8188 | AQ80: 19969 | AR80: =SUM(Y80:AD80) -> 4 | AS80: =AR80*8 -> 32
A81: 公司关联产品需求 | B81: 高 | C81: 是 | D81: 通用结构平台-自研 | E81: MxSim.Fatigue | F81: GUI | H81: 结果数据输出 | I81: 参考nCode2019，软件支持输出特定位置雨流计数后的统计结果，包括雨流幅值范围、平均值，点数等，能以表格和直方图的形式表现，方便用户分析。 软件支持输出特定位置的应力应变载荷谱数据并在界面中显示，方便用户分析。 软件支持输出特定位置的PSD计数结果数据并在界面中显示，方便用户分析。 软件支持输出特定位置的扫频计数结果数据并在界面中显示，方便用户分析。 软件支持输出特定位置的输出指定单元的定频计数结果数据并在界面中显示，方便用户分析。 | J81: 验收过程： 1.打开软件，进行软件操作，满足*关键规格与描述，满足需求文档中或项目的具体需求。 验证算例例子： 8.使用求解器测试算例，无需技术服务部及测试部额外制作算例。 测试部门：产品测试部 | K81: nCode | L81: 否 | M81: 否 | N81: 是 | O81: 7级 | P81: 张开元 | Q81: P1 | R81: P1 | S81: =SUBSTITUTE(Q81,"P","") -> 1 | T81: =SUBSTITUTE(R81,"P","") -> 1 | U81: =SUBSTITUTE(S81,"P","") -> 1 | V81: 2026 | W81: 45747 | X81: MxSim.Fatigue疲劳软件-通用-GUI-V3.0.0 | Z81: 6 | AE81: 46023 | AF81: 46112 | AP81: 8189 | AQ81: 19970 | AR81: =SUM(Y81:AD81) -> 6 | AS81: =AR81*8 -> 48
A82: 公司关联产品需求 | B82: 高 | C82: 是 | D82: 通用结构平台-自研 | E82: MxSim.Fatigue | F82: GUI | H82: 支持显示载荷谱和有限元模型应力载荷雨流幅值显示。 | I82: 支持显示载荷谱和有限元模型应力载荷雨流幅值显示。 | J82: 验收过程： 1.打开软件，进行软件操作，满足*关键规格与描述，满足需求文档中或项目的具体需求。 验证算例例子： 9.使用求解器测试算例，无需技术服务部及测试部额外制作算例。 测试部门：产品测试部 | K82: nCode | L82: 否 | M82: 否 | N82: 是 | O82: 7级 | P82: 张开元 | Q82: P1 | R82: P1 | S82: =SUBSTITUTE(Q82,"P","") -> 1 | T82: =SUBSTITUTE(R82,"P","") -> 1 | U82: =SUBSTITUTE(S82,"P","") -> 1 | V82: 2026 | W82: 45747 | X82: MxSim.Fatigue疲劳软件-通用-GUI-V3.0.0 | Z82: 5 | AE82: 46023 | AF82: 46112 | AP82: 8190 | AQ82: 19971 | AR82: =SUM(Y82:AD82) -> 5 | AS82: =AR82*8 -> 40
A83: 公司关联产品需求 | B83: 高 | C83: 是 | D83: 通用结构平台-自研 | E83: MxSim.Fatigue | F83: GUI | H83: ODS振型显示功能 | I83: 参考nCode2019，软件支持显示构件工作变形振型，便于用户观察结构在工作载荷下的动态响应。 | J83: 验收过程： 1.打开软件，进行软件操作，满足*关键规格与描述，满足需求文档中或项目的具体需求。 验证算例例子： 10.使用求解器测试算例，无需技术服务部及测试部额外制作算例。 测试部门：产品测试部 | K83: nCode | L83: 否 | M83: 否 | N83: 是 | O83: 7级 | P83: 张开元 | Q83: P1 | R83: P1 | S83: =SUBSTITUTE(Q83,"P","") -> 1 | T83: =SUBSTITUTE(R83,"P","") -> 1 | U83: =SUBSTITUTE(S83,"P","") -> 1 | V83: 2026 | W83: 45747 | X83: MxSim.Fatigue疲劳软件-通用-GUI-V3.0.0 | Z83: 6 | AE83: 46023 | AF83: 46112 | AP83: 8191 | AQ83: 19972 | AR83: =SUM(Y83:AD83) -> 6 | AS83: =AR83*8 -> 48
A84: 公司关联产品需求 | B84: 高 | C84: 是 | D84: 通用结构平台-自研 | E84: MxSim.Fatigue | F84: GUI | H84: 载荷伪损伤计算 | I84: 参考nCode2019，开发载荷谱伪损伤计算功能，以便快速评估载荷对结构的潜在影响。 | J84: 验收过程： 1.打开软件，进行软件操作，满足*关键规格与描述，满足需求文档中或项目的具体需求。 验证算例例子： 11.使用求解器测试算例，无需技术服务部及测试部额外制作算例。 测试部门：产品测试部 | K84: nCode | L84: 否 | M84: 否 | N84: 是 | O84: 7级 | P84: 张开元 | Q84: P1 | R84: P1 | S84: =SUBSTITUTE(Q84,"P","") -> 1 | T84: =SUBSTITUTE(R84,"P","") -> 1 | U84: =SUBSTITUTE(S84,"P","") -> 1 | V84: 2026 | W84: 45747 | X84: MxSim.Fatigue疲劳软件-通用-GUI-V3.0.0 | Z84: 3 | AE84: 46023 | AF84: 46112 | AP84: 8192 | AQ84: 19973 | AR84: =SUM(Y84:AD84) -> 3 | AS84: =AR84*8 -> 24
A85: 公司关联产品需求 | B85: 高 | C85: 是 | D85: 通用结构平台-自研 | E85: MxSim.Fatigue | F85: GUI | H85: 随机载荷数据统计与显示功能 | I85: 参考nCode2019，计算信号的各种统计学数据，包括平均值、均方根、标准差、方差、偏度、峰度和峰值因子并以柱状图、曲线、二维热力图显示，构建多维度的载荷损伤特征识别体系。 | J85: 验收过程： 1.打开软件，进行软件操作，满足*关键规格与描述，满足需求文档中或项目的具体需求。 验证算例例子： 12.使用求解器测试算例，无需技术服务部及测试部额外制作算例。 测试部门：产品测试部 | K85: nCode | L85: 否 | M85: 否 | N85: 是 | O85: 7级 | P85: 张开元 | Q85: P1 | R85: P1 | S85: =SUBSTITUTE(Q85,"P","") -> 1 | T85: =SUBSTITUTE(R85,"P","") -> 1 | U85: =SUBSTITUTE(S85,"P","") -> 1 | V85: 2026 | W85: 45747 | X85: MxSim.Fatigue疲劳软件-通用-GUI-V3.0.0 | Z85: 5 | AE85: 46023 | AF85: 46112 | AP85: 8193 | AQ85: 19974 | AR85: =SUM(Y85:AD85) -> 5 | AS85: =AR85*8 -> 40
A86: 公司关联产品需求 | B86: 高 | C86: 是 | D86: 通用结构平台-自研 | E86: MxSim.Fatigue | F86: GUI | H86: 时序载荷生成器优化 | I86: 时序载荷生成器与时域分析节点进行结合，实现数据传递 | J86: 验收过程： 1.打开软件，进行软件操作，满足*关键规格与描述，满足需求文档中或项目的具体需求。 验证算例例子： 13.使用求解器测试算例，无需技术服务部及测试部额外制作算例。 测试部门：产品测试部 | K86: nCode | L86: 否 | M86: 否 | N86: 是 | O86: 7级 | P86: 张开元 | Q86: P1 | R86: P1 | S86: =SUBSTITUTE(Q86,"P","") -> 1 | T86: =SUBSTITUTE(R86,"P","") -> 1 | U86: =SUBSTITUTE(S86,"P","") -> 1 | V86: 2026 | W86: 45747 | X86: MxSim.Fatigue疲劳软件-通用-GUI-V3.0.0 | Z86: 2 | AE86: 46023 | AF86: 46112 | AP86: 8194 | AQ86: 19975 | AR86: =SUM(Y86:AD86) -> 2 | AS86: =AR86*8 -> 16
A87: 公司关联产品需求 | B87: 高 | C87: 是 | D87: 通用结构平台-自研 | E87: MxSim.Fatigue | F87: GUI | H87: 频域载荷生成器优化 | I87: 扫频、定频、随机振动生成器 | J87: 验收过程： 1.打开软件，进行软件操作，满足*关键规格与描述，满足需求文档中或项目的具体需求。 验证算例例子： 14.使用求解器测试算例，无需技术服务部及测试部额外制作算例。 测试部门：产品测试部 | K87: nCode | L87: 否 | M87: 否 | N87: 是 | O87: 7级 | P87: 张开元 | Q87: P1 | R87: P1 | S87: =SUBSTITUTE(Q87,"P","") -> 1 | T87: =SUBSTITUTE(R87,"P","") -> 1 | U87: =SUBSTITUTE(S87,"P","") -> 1 | V87: 2026 | W87: 45747 | X87: MxSim.Fatigue疲劳软件-通用-GUI-V3.0.0 | Z87: 2 | AE87: 46023 | AF87: 46112 | AP87: 8195 | AQ87: 19976 | AR87: =SUM(Y87:AD87) -> 2 | AS87: =AR87*8 -> 16
... A96: 公司关联产品需求 | B96: 中 | C96: 是 | D96: 通用结构平台-自研 | E96: MxSim.Fatigue | F96: GUI | H96: 频域载荷生成器连接随机振动，扫频，定频分析节点 | I96: 频域载荷生成器连接随机振动，扫频，定频分析节点 | J96: 验收过程： 1.打开软件，进行软件操作，满足*关键规格与描述，满足需求文档中或项目的具体需求。 验证算例例子： 28.使用求解器测试算例，无需技术服务部及测试部额外制作算例。 测试部门：产品测试部 | K96: nCode | L96: 否 | M96: 否 | N96: 是 | O96: 7级 | P96: 张开元 | Q96: P1 | R96: P1 | S96: =SUBSTITUTE(Q96,"P","") -> 1 | T96: =SUBSTITUTE(R96,"P","") -> 1 | U96: =SUBSTITUTE(S96,"P","") -> 1 | V96: 2026 | W96: 45747 | X96: MxSim.Fatigue疲劳软件-通用-GUI-V3.0.0 | Z96: 2 | AE96: 46023 | AF96: 46112 | AP96: 8209 | AQ96: 19990 | AR96: =SUM(Y96:AD96) -> 2 | AS96: =AR96*8 -> 16
A97: 公司关联产品需求 | B97: 高 | C97: 是 | D97: 通用结构平台-自研 | E97: MxSim.Post | F97: GUI | H97: 切面图 | I97: 根据项目需求完成隐式后处理界面开发 | J97: 验收过程： 1.打开软件，进行软件操作，满足*关键规格与描述，满足需求文档中或项目的具体需求。 测试部门：产品测试部 | K97: Ansys-Mechanical | L97: 否 | M97: 否 | N97: 是 | O97: 3级 | P97: 孙当君 | Q97: P1 | R97: P1 | S97: 1 | T97: 1 | U97: 1 | V97: 2026 | W97: 46112 | X97: MxSim.Mechanical-通用-GUI-V3.0.0 | Z97: 7 | AE97: 46023 | AF97: 45747 | AG97: =Y97 -> 0 | AH97: =IFERROR(IF($U97=1,Z97*$AA$1,IF($U97=2,Z97*$AA$2,IF($U97=3,Z97*$AA$3,IF($U97=4,Z97*$AA$4)))),0) -> 7 | AI97: =IFERROR(IF($U97=1,AA97*$AA$1,IF($U97=2,AA97*$AA$2,IF($U97=3,AA97*$AA$3,IF($U97=4,AA97*$AA$4)))),0) -> 0 | AJ97: =IF($U97=1,AB97*$AA$1,IF($U97=2,AB97*$AA$2,IF($U97=3,AB97*$AA$3,IF($U97=4,AB97*$AA$4)))) -> 0 | AK97: =IF($U97=1,AC97*$AA$1,IF($U97=2,AC97*$AA$2,IF($U97=3,AC97*$AA$3,IF($U97=4,AC97*$AA$4)))) -> 0 | AL97: =AD97 -> 0 | AP97: 8233 | AQ97: 20014 | AR97: =SUM(Y97:AD97) -> 7 | AS97: =AR97*8 -> 56
A98: 公司关联产品需求 | B98: 高 | C98: 是 | D98: 通用结构平台-自研 | E98: MxSim.Post | F98: GUI | H98: 等值面图 | I98: 根据项目需求完成隐式后处理界面开发 | J98: 验收过程： 1.打开软件，进行软件操作，满足*关键规格与描述，满足需求文档中或项目的具体需求。 测试部门：产品测试部 | K98: Ansys-Mechanical | L98: 否 | M98: 否 | N98: 是 | O98: 3级 | P98: 孙当君 | Q98: P1 | R98: P1 | S98: 1 | T98: 1 | U98: 1 | V98: 2026 | W98: 46112 | X98: MxSim.Mechanical-通用-GUI-V3.0.0 | Z98: 5 | AE98: 46023 | AF98: 45747 | AG98: =Y98 -> 0 | AH98: =IFERROR(IF($U98=1,Z98*$AA$1,IF($U98=2,Z98*$AA$2,IF($U98=3,Z98*$AA$3,IF($U98=4,Z98*$AA$4)))),0) -> 5 | AI98: =IFERROR(IF($U98=1,AA98*$AA$1,IF($U98=2,AA98*$AA$2,IF($U98=3,AA98*$AA$3,IF($U98=4,AA98*$AA$4)))),0) -> 0 | AJ98: =IF($U98=1,AB98*$AA$1,IF($U98=2,AB98*$AA$2,IF($U98=3,AB98*$AA$3,IF($U98=4,AB98*$AA$4)))) -> 0 | AK98: =IF($U98=1,AC98*$AA$1,IF($U98=2,AC98*$AA$2,IF($U98=3,AC98*$AA$3,IF($U98=4,AC98*$AA$4)))) -> 0 | AL98: =AD98 -> 0 | AP98: 8234 | AQ98: 20015 | AR98: =SUM(Y98:AD98) -> 5 | AS98: =AR98*8 -> 40 | AT98: 3.10变更基线，人天从3变成5
A99: 公司关联产品需求 | B99: 高 | C99: 是 | D99: 通用结构平台-自研 | E99: MxSim.Post | F99: GUI | H99: 矢量图 | I99: 根据项目需求完成隐式后处理界面开发 | J99: 验收过程： 1.打开软件，进行软件操作，满足*关键规格与描述，满足需求文档中或项目的具体需求。 测试部门：产品测试部 | K99: Ansys-Mechanical | L99: 否 | M99: 否 | N99: 是 | O99: 3级 | P99: 孙当君 | Q99: P1 | R99: P1 | S99: 1 | T99: 1 | U99: 1 | V99: 2026 | W99: 46112 | X99: MxSim.Mechanical-通用-GUI-V3.0.0 | Z99: 7 | AE99: 46023 | AF99: 45747 | AG99: =Y99 -> 0 | AH99: 10 | AI99: =IFERROR(IF($U99=1,AA99*$AA$1,IF($U99=2,AA99*$AA$2,IF($U99=3,AA99*$AA$3,IF($U99=4,AA99*$AA$4)))),0) -> 0 | AJ99: =IF($U99=1,AB99*$AA$1,IF($U99=2,AB99*$AA$2,IF($U99=3,AB99*$AA$3,IF($U99=4,AB99*$AA$4)))) -> 0 | AK99: =IF($U99=1,AC99*$AA$1,IF($U99=2,AC99*$AA$2,IF($U99=3,AC99*$AA$3,IF($U99=4,AC99*$AA$4)))) -> 0 | AL99: =AD99 -> 0 | AP99: 8235 | AQ99: 20016 | AR99: =SUM(Y99:AD99) -> 7 | AS99: =AR99*8 -> 56
A100: 公司关联产品需求 | B100: 高 | C100: 是 | D100: 通用结构平台-自研 | E100: MxSim.Post | F100: GUI | H100: 曲线功能 | I100: 根据项目需求完成隐式后处理界面开发 | J100: 验收过程： 1.打开软件，进行软件操作，满足*关键规格与描述，满足需求文档中或项目的具体需求。 测试部门：产品测试部 | K100: Ansys-Mechanical | L100: 否 | M100: 否 | N100: 是 | O100: 3级 | P100: 孙当君 | Q100: P1 | R100: P1 | S100: 1 | T100: 1 | U100: 1 | V100: 2026 | W100: 46112 | X100: MxSim.Mechanical-通用-GUI-V3.0.0 | Z100: 25 | AE100: 46023 | AF100: 45747 | AG100: =Y100 -> 0 | AH100: =IFERROR(IF($U100=1,Z100*$AA$1,IF($U100=2,Z100*$AA$2,IF($U100=3,Z100*$AA$3,IF($U100=4,Z100*$AA$4)))),0) -> 25 | AI100: =IFERROR(IF($U100=1,AA100*$AA$1,IF($U100=2,AA100*$AA$2,IF($U100=3,AA100*$AA$3,IF($U100=4,AA100*$AA$4)))),0) -> 0 | AJ100: =IF($U100=1,AB100*$AA$1,IF($U100=2,AB100*$AA$2,IF($U100=3,AB100*$AA$3,IF($U100=4,AB100*$AA$4)))) -> 0 | AK100: =IF($U100=1,AC100*$AA$1,IF($U100=2,AC100*$AA$2,IF($U100=3,AC100*$AA$3,IF($U100=4,AC100*$AA$4)))) -> 0 | AL100: =AD100 -> 0 | AP100: 8238 | AQ100: 20019 | AR100: =SUM(Y100:AD100) -> 25 | AS100: =AR100*8 -> 200 | AT100: 3.10变更基线，人天从18变成25
A101: 市场需求 | B101: 高 | C101: 否 | D101: 云泊商业项目 | E101: 云泊商业项目 | F101: 云泊开发项目 | G101: 云泊界面开发 | H101: 云泊界面开发 | I101: 根据项目需求完成云泊项目开发工作 | J101: 验证标准：【无需算例，直接通过软件进行创建】 验证算例例子：【无需算例，直接进行软件测试】 | K101: 无 | L101: 否 | M101: 否 | N101: 否 | O101: 7级 | P101: 刘学文 | Q101: P1 | R101: P1 | S101: 1 | T101: 1 | U101: 1 | V101: 2026 | W101: 46112 | X101: 通用CAE前后处理和网格剖分引擎二期攻关项目（商业项目）V1.0.4 | Z101: 16 | AE101: 46023 | AF101: 46112 | AP101: 8211 | AQ101: 20022 | AR101: =SUM(Y101:AD101) -> 16 | AS101: =AR101*8 -> 128 | AT101: 3.10变更基线，人天从66变成16
A102: 公司关联产品需求 | B102: 高 | C102: 是 | D102: 783项目 | E102: 783项目 | F102: GUI | H102: 旋罩环境下大口径数字阵虚拟验证仿真软件开发 | I102: 783项目显式、隐式、流体、疲劳四个前处理软件和平台的接口适配和适配； 后处理文件的接口和功能适配 | J102: 客户验收 | K102: 无 | L102: 否 | M102: 否 | N102: 否 | O102: 7级 | P102: 邬志强 | Q102: P2 | R102: P2 | S102: 0 | T102: 1 | U102: 0 | V102: 2026 | W102: 46112 | X102: 783-旋罩环境下大口径数字阵虚拟验证仿真条件V0.0.0 | AA102: 22 | AE102: 46023 | AF102: 46112 | AP102: 8241 | AQ102: 19935 | AR102: =SUM(Y102:AD102) -> 22 | AS102: =AR102*8 -> 176
A103: 公司关联产品需求 | B103: 高 | C103: 是 | D103: 通用结构平台-自研 | E103: MxSim.Mech | F103: GUI | H103: 界面重构-与修改 | I103: 按照界面重构项目组计划和要求进行 | J103: 验收过程： 1.打开软件，进行软件操作，满足*关键规格与描述，满足需求文档中或项目的具体需求。 测试部门：产品测试部 | K103: 无 | L103: 否 | M103: 否 | N103: 是 | O103: 7级 | P103: 邬志强 | Q103: P2 | R103: P2 | S103: 0 | T103: 1 | U103: 0 | V103: 2026 | W103: 46112 | X103: MxSim.Mechanical-通用-GUI-V3.0.0 | AA103: 25 | AE103: 46023 | AF103: 46112 | AP103: 8231 | AQ103: 20012 | AR103: =SUM(Y103:AD103) -> 25 | AS103: =AR103*8 -> 200
A104: 公司关联产品需求 | B104: 高 | C104: 是 | D104: 通用结构平台-自研 | E104: MxSim.Mech | F104: GUI | H104: 界面重构-前处理 | I104: 1、根据项目需求完成隐式界面开发 2、完成已对齐关键字的mx文件读写 | J104: 验收过程： 1.打开软件，进行软件操作，满足*关键规格与描述，满足需求文档中或项目的具体需求。 测试部门：产品测试部 | K104: Ansys-Mechanical | L104: 否 | M104: 否 | N104: 是 | O104: 3级 | P104: 宋维超 | Q104: P1 | R104: P1 | S104: 1 | T104: 1 | U104: 1 | V104: 2026 | W104: 46112 | X104: MxSim.Mechanical-通用-GUI-V3.0.0 | Z104: 25 | AE104: 46023 | AF104: 46112 | AP104: 8229 | AQ104: 20008 | AR104: =SUM(Y104:AD104) -> 25 | AS104: =AR104*8 -> 200
A105: 公司关联产品需求 | B105: 高 | C105: 是 | D105: 通用结构平台-自研 | E105: MxSim.Mech | F105: GUI | H105: 界面重构-工程文件 | I105: 完成已对齐的所有关键字工程文件的读写 | J105: 验收过程： 1.打开软件，进行软件操作，满足*关键规格与描述，满足需求文档中或项目的具体需求。 测试部门：产品测试部 | K105: Ansys-Mechanical | L105: 否 | M105: 否 | N105: 是 | O105: 3级 | P105: 宋维超 | Q105: P1 | R105: P1 | S105: 1 | T105: 1 | U105: 1 | V105: 2026 | W105: 46112 | X105: MxSim.Mechanical-通用-GUI-V3.0.0 | Z105: 10 | AE105: 46023 | AF105: 46112 | AP105: 8506 | AQ105: 20297 | AR105: =SUM(Y105:AD105) -> 10 | AS105: =AR105*8 -> 80
A106: 公司关联产品需求 | B106: 高 | C106: 是 | D106: 通用结构平台-自研 | E106: MxSim.Mech | F106: GUI | H106: 界面重构-多分析并行求解 | I106: 1、支持选定分析与所有分析一同求解器，通过并行导出文件与同时求解 2、解决多线程导出时，映射数据冲突问题 | J106: 验收过程： 1.打开软件，进行软件操作，满足*关键规格与描述，满足需求文档中或项目的具体需求。 测试部门：产品测试部 | K106: Ansys-Mechanical | L106: 否 | M106: 否 | N106: 否 | O106: 3级 | P106: 宋维超 | Q106: P1 | R106: P1 | S106: 1 | T106: 1 | U106: 1 | V106: 2026 | W106: 46112 | X106: MxSim.Mechanical-通用-GUI-V3.0.0 | Z106: 8 | AE106: 46023 | AF106: 46112 | AP106: 8507 | AQ106: 20298 | AR106: =SUM(Y106:AD106) -> 8 | AS106: =AR106*8 -> 64
A107: 公司关联产品需求 | B107: 高 | C107: 是 | D107: 通用结构平台-自研 | E107: MxSim.Mech | F107: GUI | H107: 界面重构-底层数据 | I107: 1、维护现有数据接口 2、根据其他模块需求添加新接口 | J107: 验收过程： 1.打开软件，进行软件操作，满足*关键规格与描述，满足需求文档中或项目的具体需求。 测试部门：产品测试部 | K107: Ansys-Mechanical | L107: 否 | M107: 否 | N107: 是 | O107: 3级 | P107: 宋维超 | Q107: P1 | R107: P1 | S107: 1 | T107: 1 | U107: 1 | V107: 2026 | W107: 46112 | X107: MxSim.Mechanical-通用-GUI-V3.0.0 | Z107: 8 | AE107: 46023 | AF107: 46112 | AP107: 8228 | AQ107: 20009 | AR107: =SUM(Y107:AD107) -> 8 | AS107: =AR107*8 -> 64
A108: 公司关联产品需求 | B108: 高 | C108: 是 | D108: 通用结构平台-自研 | E108: MxSim.Mech | F108: GUI | H108: 界面重构-模型树 | I108: 1、优化模型树使用体验 2、添加新节点与新接口 3、模型树节点状态更新 | J108: 验收过程： 1.打开软件，进行软件操作，满足*关键规格与描述，满足需求文档中或项目的具体需求。 测试部门：产品测试部 | K108: Ansys-Mechanical | L108: 否 | M108: 否 | N108: 是 | O108: 3级 | P108: 宋维超 | Q108: P1 | R108: P1 | S108: 1 | T108: 1 | U108: 1 | V108: 2026 | W108: 46112 | X108: MxSim.Mechanical-通用-GUI-V3.0.0 | Z108: 10 | AE108: 46023 | AF108: 46112 | AP108: 8508 | AQ108: 20299 | AR108: =SUM(Y108:AD108) -> 10 | AS108: =AR108*8 -> 80
A109: 公司关联产品需求 | B109: 高 | C109: 是 | D109: 多物理场智算平台-自研 | E109: MxSim.CFD | F109: GUI | H109: 多边形网格支持 | I109: 1.支持流体多边形、多面体网格信息 | J109: 验收过程： 1.打开软件，进行软件操作，满足*关键规格与描述，满足需求文档中或项目的具体需求。 测试部门：产品测试部 | K109: Ansys-Fluent | L109: 否 | M109: 否 | N109: 否 | O109: 3级 | P109: 宋维超 | Q109: P1 | R109: P1 | S109: 1 | T109: 1 | U109: 1 | V109: 2026 | W109: 46112 | X109: MxSim.CFD可压流体软件开发项目-GUI-V2.0.0 | Z109: 16 | AP109: 9096 | AQ109: 21464
...

Sheet 基线总计月份
A1: MxSim单元材料产品基线表已完成基线核算，整个产品人力管道为0.98，明细如下:
A2: 姓名 | B2: 在职/离职 | C2: 人员属性 | D2: 最早入职日期 | E2: 2025年当前已经规划人力预算月数 | F2: 2025年人力规划 | G2: 2025年人力预测 | H2: 2025年的人力实际核算 | I2: 2025年人力管道 | J2: 预留人力月数 | K2: 人力管道 | L2: 备注
A18: 汇总 | E18: =SUM(E3:E17) -> 0 | H18: =SUM(H3:H17) -> 0 | I18: =SUM(I3:I17) -> 0
A19: 总人力管道 | E19: =E18/I18 -> #DIV/0!

Sheet 每月复核总表
A1: 人员SAP部门 | B1: 费用来源部门 | C1: 姓名 | D1: 2025年规划人力预算天 | E1: 基线任务安排（天）（1-12月） | F1: 基线任务安排（1-12月） | G1: 基线实际投入（天）截至到（9月） | H1: 基线实际投入（天）截至到（12月31日） | I1: 外协支撑（天数） | J1: 工时记录1-9月份（天） | K1: 外协+基线投入 | L1: 偏差（基线偏差） | M1: 工时与基线偏差 | N1: 工时合理性复核 | O1: 备注
A2: 产品技术部 | B2: 产品技术部
A3: 产品技术部 | B3: 产品技术部
A4: 产品技术部 | B4: 产品技术部
A5: 产品技术部 | B5: 产品技术部
A6: 产品技术部 | B6: 产品技术部
A7: 产品技术部 | B7: 产品技术部
A8: 产品技术部 | B8: 产品技术部
A9: 产品技术部 | B9: 产品技术部
A10: 产品技术部 | B10: 产品技术部
A11: 产品技术部 | B11: 产品技术部
A12: 产品技术部 | B12: 产品技术部 | O12: 实习生
A13: 产品技术部 | B13: 产品技术部 | O13: 已离职
A14: 产品技术部 | B14: 产品技术部 | O14: 实习生
A15: 产品技术部 | B15: 产品技术部 | O15: 实习生
A16: 产品技术部 | B16: 产品技术部 | O16: 实习生

Sheet 单人工作天数
A1: 第一季度
A2: 姓名 | B2: 工时 | C2: 预算时间 | D2: 时间差额 | E2: 人员等级
A3: 汤光泽 | B3: =SUMIF('2026Q1'!P:P,A3,'2026Q1'!AC:AC) -> 72 | C3: 66 | D3: =B3-C3 -> 6 | E3: P4
A4: 宋维超 | B4: =SUMIF('2026Q1'!P:P,A4,'2026Q1'!Z:Z) -> 82 | C4: 66 | D4: =B4-C4 -> 16 | E4: P1
A5: 张开元 | B5: =SUMIF('2026Q1'!P:P,A5,'2026Q1'!Z:Z) -> 65 | C5: 66 | D5: =B5-C5 -> -1 | E5: P1
A6: 刘学文 | B6: =SUMIF('2026Q1'!P:P,A6,'2026Q1'!Z:Z) -> 66 | C6: 66 | D6: =B6-C6 -> 0 | E6: P1
A7: 向强 | B7: =SUMIF('2026Q1'!P:P,A7,'2026Q1'!AA:AA) -> 66 | C7: 66 | D7: =B7-C7 -> 0 | E7: P2
A8: 刘奉明 | B8: =SUMIF('2026Q1'!P:P,A8,'2026Q1'!Z:Z) -> 66 | C8: 66 | D8: =B8-C8 -> 0 | E8: P1
A9: 孙当君 | B9: =SUMIF('2026Q1'!P:P,A9,'2026Q1'!Z:Z) -> 66 | C9: 66 | D9: =B9-C9 -> 0 | E9: P1
A10: 王飞奇 | B10: =SUMIF('2026Q1'!P:P,A10,'2026Q1'!Z:Z) -> 72 | C10: 66 | D10: =B10-C10 -> 6 | E10: P1
A11: 胡旭杰 | B11: =SUMIF('2026Q1'!P:P,A11,'2026Q1'!Y:Y) -> 37 | C11: 66 | D11: =B11-C11 -> -29 | E11: SX
A12: 曹业鸿 | B12: =SUMIF('2026Q1'!P:P,A12,'2026Q1'!Y:Y) -> 66 | C12: 66 | D12: =B12-C12 -> 0 | E12: SX
A13: 王海东 | B13: =SUMIF('2026Q1'!P:P,A13,'2026Q1'!Z:Z) -> 66 | C13: 66 | D13: =B13-C13 -> 0 | E13: P1
A14: 殷思麒 | B14: =SUMIF('2026Q1'!P:P,A14,'2026Q1'!Z:Z) -> 75 | C14: 66 | D14: =B14-C14 -> 9 | E14: P1
A15: 彭武绍 | B15: =SUMIF('2026Q1'!P:P,A15,'2026Q1'!AA:AA) -> 66 | C15: 66 | D15: =B15-C15 -> 0 | E15: P2
A16: 林家正 | B16: =SUMIF('2026Q1'!P:P,A16,'2026Q1'!Z:Z) -> 68 | C16: 66 | D16: =B16-C16 -> 2 | E16: P1
A17: 潜森伟 | B17: =SUMIF('2026Q1'!P:P,A17,'2026Q1'!Z:Z) -> 68 | C17: 66 | D17: =B17-C17 -> 2 | E17: P1
A18: 黄育民 | B18: =SUMIF('2026Q1'!P:P,A18,'2026Q1'!Y:Y) -> 77 | C18: 66 | D18: =B18-C18 -> 11 | E18: SX
A19: 李靓杰 | B19: =SUMIF('2026Q1'!P:P,A19,'2026Q1'!AA:AA) -> 66 | C19: 66 | D19: =B19-C19 -> 0 | E19: P2
A20: 李瑞阳 | B20: =SUMIF('2026Q1'!P:P,A20,'2026Q1'!Z:Z) -> 66 | C20: 66 | D20: =B20-C20 -> 0 | E20: P1
A21: 李政斌 | B21: =SUMIF('2026Q1'!P:P,A21,'2026Q1'!AA:AA) -> 66 | C21: 66 | D21: =B21-C21 -> 0 | E21: P2
A22: 肖志钢 | B22: =SUMIF('2026Q1'!P:P,A22,'2026Q1'!Z:Z) -> 66 | C22: 66 | D22: =B22-C22 -> 0 | E22: P1
A23: 邬志强 | B23: =SUMIF('2026Q1'!P:P,A23,'2026Q1'!AA:AA) -> 72 | C23: 66 | D23: =B23-C23 -> 6 | E23: P2
A24: 吴维煜 | B24: =SUMIF('2026Q1'!P:P,A24,'2026Q1'!AA:AA) -> 66 | C24: 66 | D24: =B24-C24 -> 0 | E24: P2
A25: 张国海 | B25: =SUMIF('2026Q1'!P:P,A25,'2026Q1'!AA:AA) -> 68 | C25: 66 | D25: =B25-C25 -> 2 | E25: P2

Sheet 人工测算表
A1: 项目人工费工时定额
G2: 单位：元
A3: 序号 | B3: 人员职级分类 | C3: 内部预算定额 | E3: 外部收费定额 | G3: 备 注
C4: 费率（元/人天） | D4: 费率（元/人月） | E4: 费率（元/人天） | F4: 费率（元/人月）
A5: 1 | B5: 实习 | C5: 330 | D5: 7000 | G5: 1.项目人员费用定额依据公司研发薪酬职位体系表对应职级B职等起薪、福利、费用标准上浮一定系数（约10%）测定； 2.实习人员按P1级的50%预估； 3.本定额为2023年～2024年参考定额。
A6: 2 | B6: P1 | C6: 650 | D6: 14000
A7: 3 | B7: P2 | C7: 1000 | D7: 22000
A8: 4 | B8: P3 | C8: 1350 | D8: 29000
A9: 5 | B9: P4 | C9: 1700 | D9: 37000
A10: 6 | B10: P5 | C10: 2100 | D10: 45000
A11: 7 | B11: P6 | C11: 2500 | D11: 55000
A12: 8 | B12: P7 | C12: 3000 | D12: 65000
L13: 单位：万元
A14: 序号 | B14: 主要工作任务 | C14: 实习人月 | D14: P1人天 | E14: P2人天 | F14: P3人天 | G14: P4人天 | H14: P5人天 | I14: P6人天 | J14: P7人天 | K14: 临聘人工费（实习） | L14: 项目人工费（正式）
A15: 1 | B15: MxDesign.NodeFlow开发 | D15: 58 | E15: 159 | F15: 0 | G15: 0 | L15: =(D15*C6+E15*C7+F15*$C$8+G15*$C$9+H15*$C$10+I15*$C$11+J15*$C$12)/10000 -> 19.67
A16: 2 | B16: MxDesign.Wizard开发 | D16: 0 | E16: 66 | F16: 0 | L16: =(D16*$C$6+E16*$C$7+F16*$C$8+G16*$C$9+H16*$C$10+I16*$C$11+J16*$C$12)/10000 -> 6.6
B17: 合计 | C17: =SUM(C15:C16) -> 0 | D17: =SUM(D15:D16) -> 58 | E17: =SUM(E15:E16) -> 225 | F17: 0 | G17: =SUM(G15:G16) -> 0 | H17: =SUM(H15:H16) -> 0 | I17: =SUM(I15:I16) -> 0 | J17: =SUM(J15:J16) -> 0 | K17: =SUM(K15:K16) -> 0 | L17: =SUM(L15:L16) -> 26.27
A18: 说明：
A19: 1.预算定额可以选择按人天或人月，测算时请选择对应预算定额。
A20: 2.如栏次不够，请在合计栏前一栏添行。
C25: 唐达 | D25: P1
C26: 龙旺 | D26: P2
C27: 任文杰 | D27: P2
C28: 廖孟亮 | D28: P2
C29: 文豪 | D29: P1

Sheet 项目预算表
A1: 迈 曦 软 件 项 目 预 算 表
E2: 单位：万元
A3: 项目名称 | B3: 迈曦多学科优化设计软件MxDesign
A4: 项目类别 | B4: 自研 | D4: 项目号
A5: 项目收入（A)
A6: 项目费用类别 | B6: 项目费用明细 | C6: 项目组申报 | D6: 审核金额 | E6: 备 注
A7: 项目人工 | B7: 1.项目人工费 | C7: ='[2]项目人工费工时定额 '!L17 -> 26.27 | E7: 项目组报项目人员职级及工时，套用人工定额测算费用。
B8: 2.临聘人工费 | C8: =[1]项目人工测算表!K17 -> 0 | E8: 项目组报项目实习人员工时，套用人工定额测算费用。
B9: 小计 | C9: =SUM(C7:C8) -> 26.27
A10: 项目实施成本 | B10: 1.材料费 | C10: 0 | E10: 消耗的各种原材料、辅助材料、低值易耗品等的采购费用。
B11: 2.燃料动力费 | C11: 0 | E11: 直接消耗的各种燃料动力费用。
B12: 3.测试化验加工费 | C12: 0 | E12: 支付给外单位的检验、测试、化验及加工等费用。
B13: 4.软件、仪器、设备购买及租赁费 | C13: 0 | E13: 租用设备而发生的费用及购买设备、软件的费用。
B14: 5.新产品设计费等 | C14: 0 | E14: 新产品所发生的新产品设计费。 为新产品和新工艺的构思、开发和制造，进行工序、技术规范、操作特性方面的设计等发生的费用。
B15: 6.出版/文献/信息传播/知识产权事务费 | E15: 出版费、资料费、专用软件购买费、软件许可费用、软件维保费用、购买咨询报告发生的费用、文献检索费、查新费、专业通信费、专利申请及其他知识产权事务等费用。
B16: 7.专家咨询费 | C16: 0 | E16: 支付给临时聘请的咨询专家的费用。
B17: 8.差旅费 | C17: 3 | E17: 开展业务调研、学术交流、项目实施等所发生的外埠差旅费、市内交通费用等。
B18: 9.会议费 | C18: 0.5 | E18: 开展学术研讨、咨询以及协调项目（含项目启动、阶段验收、半年及年度项目总结等）等活动而发生的会议费用。
B19: 10.鉴定、评审、评估、验收费用 | C19: 0 | E19: 聘请中介机构鉴定、评审、评估、验收费用及合作方项目验收等费用。
B20: 11.其他支出 | C20: 0
B21: 小计 | C21: =SUM(C10:C20) -> 3.5
A22: 项目委外费用 | B22: 委托研发费用
A23: 公共费用分摊 | B23: 1、折旧费用 | E23: 财务按工时分摊。
B24: 2、无形资产摊销 | E24: 财务按工时分摊。
B25: 3、公共费用分摊 | E25: 房租，日常水、电、气消耗，公共管理费用支出等。财务按工时分摊。
B26: 小计
A27: 项目费用合计（B） | C27: =C21+C9 -> 29.77
A28: 项目税金（C)
A29: 项目边际贡献（D=A-B-C）
A30: 审批签字 | C30: 项目经理签字 | D30: 审核人员签字
A34: 说明：
A35: 1.项目类别分自研、商业、国拨三大类。
A36: 2.项目号由财务根据编号规则填写。
A37: 3.表格数据单位以万元列示，请勿随意改动表格内公式；备注栏可简单说明预算依据，若无相关科目则无需填写明细。
A38: 4.公共费用分摊立项时暂不填写，项目实施过程中由财务按工时分摊，项目考核时并入项目成本。
A39: 5.测算日期从立项日期开始。

Sheet 个人人天统计
A1: 模块 | B1: 人员 | C1: 求和项:SX | D1: 求和项:P1 | E1: 求和项:P2 | F1: 求和项:P3 | G1: 计数项:P4 | H1: 总计
A2: NodeFlow | B2: 廖孟亮 | E2: 20 | H2: =SUM(C2:G2) -> 20
B3: 任文杰 | E3: 128 | H3: =SUM(C3:G3) -> 128
B4: 龙旺 | E4: 103 | H4: =SUM(C4:G4) -> 103
B5: 唐达 | D5: 107 | H5: =SUM(C5:G5) -> 107
B6: 文豪 | D6: 67 | H6: =SUM(C6:G6) -> 67
A7: Wizard | B7: 廖孟亮 | E7: 116 | H7: =SUM(C7:G7) -> 116
B8: 龙旺 | E8: 21 | H8: =SUM(C8:G8) -> 21
B9: 唐达 | D9: 30 | H9: =SUM(C9:G9) -> 30
B10: 文豪 | D10: 76 | H10: =SUM(C10:G10) -> 76
A11: 总计 | C11: =SUM(C2:C10) -> 0 | D11: =SUM(D2:D10) -> 280 | E11: =SUM(E2:E10) -> 388 | F11: =SUM(F2:F10) -> 0 | G11: =SUM(G2:G10) -> 0 | H11: =SUM(C11:G11) -> 668
